{
    "url": "https://scp-wiki.wikidot.com/scp-2577",
    "all_text": "rating:\u00a0\n+90\n+\n\u2013\nx\n\n\nItem #:\n SCP-2577\n\n\nObject Class:\n Euclid\n\n\nSpecial Containment Procedures:\n Foundation web-crawlers and embedded personnel in the entertainment industry are to monitor for and prevent any distribution of SCP-2577. Copyrights have been registered under Foundation front corporations for this purpose.\n\n\nMobile Task Force Alpha-4 (\u201cPony Express\u201d)\n are to intercept all international shipments to individuals credited in SCP-2577 (See Document SCP-2577-Rho for a complete list) and confiscate any packages ostensibly originating from SCP-2577-A. All confiscated items should be treated as anomalous until confirmed otherwise.\n\n\nPer standing policy, all investigations into former \nGRU Division P\n revenue practices are consolidated under Foundation Intelligence Agency operation GOLD RUSH. Reconnaissance efforts to locate SCP-2577-A have been discontinued, pending IA approval.\n\n\nDescription:\n SCP-2577 is a 2005 documentary series titled \u201cFrozen Steel\u201d occasionally appearing on streaming video services or small-scale physical media releases. SCP-2577 purportedly documents the operation and daily lives of the staff of SCP-2577-A, a decommissioning yard ostensibly located in \u2588\u2588\u2588\u2588\u2588\u2588\u2588, Siberian Federal District, Russia, used for the disposal of military ships ranging in age from the early to mid-twentieth century. SCP-2577-A consists of a single central command tower and barracks surrounded by a \u2588\u2588 square km runway constructed from level, packed tundra. Ships are delivered to this runway through means never expressed in the documentary, arriving ballistically at speeds exceeding 900\u00a0km/h before violently embedding themselves in the runway.\n\n\nSCP-2577 goes to great lengths to describe the extreme danger faced by the individuals conducting recovery operations, who are responsible for stripping ships of valuable material, breaking down and scrapping their hulls, and, if possible, repairing the runway, under the constant threat of being in the path of one of over \u2588\u2588\u2588 new ships entering SCP-2577-A on a daily basis. The few ship names or designations displayed in SCP-2577 do not match any known vessels, and the rate of ships entering SCP-2577-A far outstrips both the documented decommissioning and construction of Russian military vessels.\n\n\nThe following episode transcript, typical of SCP-2577, was retrieved from the \u2588\u2588\u2588\u2588\u2588 streaming video service.\n\n\n\n\nS01E04\n\nAnton and Team Odin race against time to remove the flight deck from the perilously listing \nAdmiral Nikolai Yezhov\n. Demolition charges may allow them to shed the dead weight and stabilize the hull, but failure could collapse the ship into unrecoverable slag.\n\n\nMeanwhile, Misha and Team Dva continue to lose men and equipment to the labyrinthine wreck of the hospital-ship \nSankt-Iakov\n. All of their work comes to naught as the incoming submarine \nTK-455\n collides with the converted freighter, reducing her to a shattered heap.\n\n\n\n\nSCP-2577 appears to have been funded, directed, and narrated by American actor Ron Perlman. Perlman is revealed in director\u2019s commentary in a home blu-ray release to have a deep admiration and personal connection to SCP-2577-A, stating that he corresponds regularly with the operators, identifying rare items salvaged from the hulks and returning them free of charge.\n\n\nPerlman and other individuals credited in SCP-2577 have failed to provide any further information on the documentary, and have been amnesticized and released following interviews. In spite of Perlman\u2019s stated ignorance of the project and lack of qualifications as an antiquarian, MTF Alpha-4 annually intercepts approximately \u2588\u2588 tons of assorted naval equipment addressed to him for appraisal. Notable confiscated objects are listed in Document SCP-2577-1.\n\n\nAerial and satellite surveillance of the area believed to contain SCP-2577-A has proven inconclusive, and overland approaches have failed to locate the facility. Investigation into West Siberian steel production and former GRU-P revenue stream D-584 (Codename: \u0421\u0430\u0434\u043a\u043e) is ongoing.\n\n\nDocument SCP-2577-1: Items purportedly originating from SCP-2577-A\n\n\n\n\nAccess\u00a0documentation.\n\n\n\n\nAccess\u00a0granted.\n\n\n\n\n\n\n\n\nObject\n\n\nDescription\n\n\nDisposition\n\n\n\n\n\n\nObject 2577-215-217\n\n\nIron chest containing one SA-18 \"Grouse\" man-portable surface-to-air missile. Warhead is constructed of precious materials in style of Peter Carl Faberg\u00e9. Payload has been replaced by one 4\u00a0cm iron needle suspended in empty canister.\n\n\nStored in Site-76 Secure Armaments Wing.\n\n\n\n\n\n\nObject 2577-314-329\n\n\nFragments of maple wood and silver wire displaying workmanship and material appropriate to 12th-century CE stringed instruments.\n\n\nStored at Site 77 pending discovery of additional items.\n\n\n\n\n\n\nAO-11824 (1-205)\n\n\n205 uniform name plates (ranks and style circa 1915) crafted from gold/copper alloy. Plates are buoyant in water regardless of density.\n\n\nRemanded to Anomalous Object processing.\n\n\n\n\n\n\nAO-11825\n\n\nOne lacquered pinewood officer's door plaque. Sinks in water regardless of density.\n\n\nRemanded to Anomalous Object processing.\n\n\n\n\n\n\n\n\n\n\n\n\n\n\nDocument SCP-2577-2: Select portions of the \n19\u2588\u2588 IA Report on Anomalous Revenue Practices in the GRU-P\n\n\n\n\n\n\nLevel\u00a03/2577\u00a0Clearance\u00a0required.\u00a0Please\u00a0enter\u00a0credentials.\n\n\n\n\nAccess\u00a0granted.\n\n\n\n\n\n\nBy \u2588\u2588/\u2588\u2588/19\u2588\u2588, persistent surveillance of known GRU-P front organizations and operatives had demonstrated that any substantial, covert GRU-P financial transaction requires one or more parties to consult a copy of \nThe Bylina as Collected by \u2588. \u2588. \u2588\u2588\u2588\u2588\u2588\u2588, 18\u2588\u2588\n, a collection of Russian folkloric sung epic poems. Continued difficulty in tracking GRU-P financial activity has led to several theories of the purpose of this volume, including:\n\n- Use in non-anomalous encryption techniques (e.g., book ciphers)\n\n- Use of the books to transport memetically camouflaged text\n\n- Use as a temporary inoculant to anti-memetic or cognition-spoofing text\n\n- Shared access point for interdimensional or retro-causitive information storage\n\n- Sympathetic \nthaumaturgic\n focus for anomalously concealed information based on thematically-relevant code-phrases\n\n- Thaumaturgic focus for anomalous fund creation\n\nThis volume is known to contain an expanded number of common bylina, including:\n\n\u2588\u2588\u2588\u2588\u2588\u2588\u2588\u2588\u2588\u2588\u2588\u2588\u2588\u2588\u2588\u2588\u2588\u2588\u2588\u2588\u2588\u2588\u2588\u2588\n\n\u2588\u2588\u2588\u2588\u2588\u2588\u2588\u2588\u2588\u2588\u2588\u2588\u2588\u2588\u2588\u2588\u2588\u2588\u2588\u2588\u2588\u2588\u2588\u2588\u2588\u2588\u2588\n\n\u0421\u0430\u0434\u043a\u043e\n\n\u2588\u2588\u2588\u2588\u2588\u2588\u2588\u2588\u2588\u2588\u2588\u2588\u2588\n\n(Page 17/35)\n\n\n\n\n\n\nSummary of selected Bylina (continued)\n\n\u2588\u2588\u2588\u2588\u2588\u2588\u2588\u2588\u2588\u2588\u2588\u2588\u2588\u2588\u2588\u2588\u2588\u2588\u2588\u2588\u2588\u2588\u2588\u2588\u2588\u2588\u2588\u2588\u2588\u2588\u2588\u2588\u2588\u2588\u2588\u2588\u2588\u2588\u2588\u2588\u2588\u2588\u2588\u2588\u2588\u2588\u2588\u2588\u2588\u2588\u2588\u2588\u2588\u2588\u2588\u2588\u2588\u2588\u2588\u2588\u2588\u2588\u2588\n\n\u2588\u2588\u2588\u2588\u2588\u2588\u2588\u2588\u2588\u2588\u2588\u2588\u2588\u2588\u2588\u2588\u2588\u2588\u2588\u2588\u2588\u2588\u2588\u2588\u2588\u2588\u2588\u2588\u2588\u2588\u2588\u2588\u2588\u2588\u2588\u2588\u2588\u2588\u2588\u2588\u2588\u2588\u2588\u2588\u2588\u2588\u2588\u2588\u2588\u2588\u2588\u2588\u2588\u2588\u2588\u2588\u2588\u2588\u2588\u2588\u2588\u2588\u2588\n\n\u2588\u2588\u2588\u2588\u2588\u2588\u2588\u2588\u2588\u2588\u2588\u2588\u2588\u2588\u2588\u2588\u2588\u2588\u2588\u2588\u2588\u2588\u2588\u2588\u2588\u2588\u2588\u2588\u2588\u2588\u2588\u2588\u2588\u2588\u2588\u2588\u2588\u2588\u2588\u2588\u2588\u2588\u2588\u2588\u2588\u2588\u2588\u2588\u2588\u2588\n\n\n\u0421\u0430\u0434\u043a\u043e (Sadko)\n\nThe musician Sadko becomes a wealthy merchant through the aid of the Water Tsar, but refuses to pay tribute when his ships pass over the sea. His fleet is becalmed, and after casting lots Sadko is forced to give himself to the sea to save his sailors. Sadko is brought before the Water Tsar and Tsarina to settle an argument: Which is more valuable in Novgorod above, iron or gold? Sadko explains that iron is more valuable because it is necessary for daily life, enraging the Water Tsar. Sadko calms the Tsar by playing his gusli, but the Tsar\u2019s wild dancing thrashes the oceans, causing many ships to be smashed upon the sea.\n\n\u2588\u2588\u2588\u2588\u2588\u2588\u2588\u2588\u2588\u2588\u2588\u2588\u2588\n\n\u2588\u2588\u2588\u2588\u2588\u2588\u2588\u2588\u2588\u2588\u2588\u2588\u2588\u2588\u2588\u2588\u2588\u2588\u2588\u2588\u2588\u2588\u2588\u2588\u2588\u2588\u2588\u2588\u2588\u2588\u2588\u2588\u2588\u2588\u2588\u2588\u2588\u2588\u2588\u2588\u2588\u2588\u2588\u2588\u2588\u2588\u2588\u2588\u2588\u2588\u2588\u2588\u2588\u2588\u2588\u2588\u2588\u2588\u2588\u2588\u2588\u2588\u2588\n\n\u2588\u2588\u2588\u2588\u2588\u2588\u2588\u2588\u2588\u2588\u2588\u2588\u2588\u2588\u2588\u2588\u2588\u2588\u2588\u2588\u2588\u2588\u2588\u2588\u2588\u2588\u2588\u2588\u2588\u2588\u2588\u2588\u2588\u2588\u2588\u2588\u2588\u2588\u2588\u2588\u2588\u2588\u2588\u2588\u2588\u2588\u2588\u2588\u2588\u2588\u2588\u2588\u2588\u2588\u2588\u2588\u2588\u2588\u2588\u2588\u2588\u2588\u2588\n\n\u2588\u2588\u2588\u2588\u2588\u2588\u2588\u2588\u2588\u2588\u2588\u2588\u2588\u2588\u2588\u2588\u2588\u2588\u2588\u2588\u2588\u2588\u2588\u2588\u2588\u2588\u2588\u2588\u2588\u2588\u2588\u2588\u2588\u2588\u2588\u2588\u2588\u2588\u2588\u2588\u2588\u2588\u2588\u2588\u2588\u2588\u2588\u2588\u2588\u2588\u2588\u2588\u2588\u2588\u2588\u2588\u2588\u2588\u2588\u2588\u2588\u2588\u2588\n\n(Page 22/35)\n\n\n\n\n\n\nEND SELECTED PORTIONS. Full report available from RAISA to personnel with GREAT GAME clearance.\n\n\n\n\n\n\n\n\n\n\n\n\n\n\n\n\n\u00ab \nSCP-2576\n | SCP-2577 | \nSCP-2578\n \u00bb\n\n\n\n\n\n\n\n\n\n\n\u2021\u00a0Licensing\u00a0/\u00a0Citation\n\n\n\n\n\u2021\u00a0Hide\u00a0Licensing\u00a0/\u00a0Citation\n\n\n\n\nCite this page as:\n\n\n \n\n\n\n\n\"\nSCP-2577\n\" by Petrograd, from the \nSCP Wiki\n. Source: \nhttps://scpwiki.com/scp-2577\n. Licensed under \nCC-BY-SA\n.\n\n\n\n\n\n\n\n\nFor information on how to use this component, see the \nLicense Box component\n. To read about licensing policy, see the \nLicensing Guide\n.",
    "addendums": [],
    "documents": [
        "Document SCP-2577-1: Items purportedly originating from SCP-2577-A\n\n\n\n"
    ],
    "notes": [
        "S01E04 Anton and Team Odin race against time to remove the flight deck from the perilously listing Admiral Nikolai Yezhov . Demolition charges may allow them to shed the dead weight and stabilize the hull, but failure could collapse the ship into unrecoverable slag. Meanwhile, Misha and Team Dva continue to lose men and equipment to the labyrinthine wreck of the hospital-ship Sankt-Iakov . All of their work comes to naught as the incoming submarine TK-455 collides with the converted freighter, reducing her to a shattered heap.",
        "By \u2588\u2588/\u2588\u2588/19\u2588\u2588, persistent surveillance of known GRU-P front organizations and operatives had demonstrated that any substantial, covert GRU-P financial transaction requires one or more parties to consult a copy of The Bylina as Collected by \u2588. \u2588. \u2588\u2588\u2588\u2588\u2588\u2588, 18\u2588\u2588 , a collection of Russian folkloric sung epic poems. Continued difficulty in tracking GRU-P financial activity has led to several theories of the purpose of this volume, including: - Use in non-anomalous encryption techniques (e.g., book ciphers) - Use of the books to transport memetically camouflaged text - Use as a temporary inoculant to anti-memetic or cognition-spoofing text - Shared access point for interdimensional or retro-causitive information storage - Sympathetic thaumaturgic focus for anomalously concealed information based on thematically-relevant code-phrases - Thaumaturgic focus for anomalous fund creation This volume is known to contain an expanded number of common bylina, including: \u2588\u2588\u2588\u2588\u2588\u2588\u2588\u2588\u2588\u2588\u2588\u2588\u2588\u2588\u2588\u2588\u2588\u2588\u2588\u2588\u2588\u2588\u2588\u2588 \u2588\u2588\u2588\u2588\u2588\u2588\u2588\u2588\u2588\u2588\u2588\u2588\u2588\u2588\u2588\u2588\u2588\u2588\u2588\u2588\u2588\u2588\u2588\u2588\u2588\u2588\u2588 \u0421\u0430\u0434\u043a\u043e \u2588\u2588\u2588\u2588\u2588\u2588\u2588\u2588\u2588\u2588\u2588\u2588\u2588 (Page 17/35)",
        "Summary of selected Bylina (continued) \u2588\u2588\u2588\u2588\u2588\u2588\u2588\u2588\u2588\u2588\u2588\u2588\u2588\u2588\u2588\u2588\u2588\u2588\u2588\u2588\u2588\u2588\u2588\u2588\u2588\u2588\u2588\u2588\u2588\u2588\u2588\u2588\u2588\u2588\u2588\u2588\u2588\u2588\u2588\u2588\u2588\u2588\u2588\u2588\u2588\u2588\u2588\u2588\u2588\u2588\u2588\u2588\u2588\u2588\u2588\u2588\u2588\u2588\u2588\u2588\u2588\u2588\u2588 \u2588\u2588\u2588\u2588\u2588\u2588\u2588\u2588\u2588\u2588\u2588\u2588\u2588\u2588\u2588\u2588\u2588\u2588\u2588\u2588\u2588\u2588\u2588\u2588\u2588\u2588\u2588\u2588\u2588\u2588\u2588\u2588\u2588\u2588\u2588\u2588\u2588\u2588\u2588\u2588\u2588\u2588\u2588\u2588\u2588\u2588\u2588\u2588\u2588\u2588\u2588\u2588\u2588\u2588\u2588\u2588\u2588\u2588\u2588\u2588\u2588\u2588\u2588 \u2588\u2588\u2588\u2588\u2588\u2588\u2588\u2588\u2588\u2588\u2588\u2588\u2588\u2588\u2588\u2588\u2588\u2588\u2588\u2588\u2588\u2588\u2588\u2588\u2588\u2588\u2588\u2588\u2588\u2588\u2588\u2588\u2588\u2588\u2588\u2588\u2588\u2588\u2588\u2588\u2588\u2588\u2588\u2588\u2588\u2588\u2588\u2588\u2588\u2588 \u0421\u0430\u0434\u043a\u043e (Sadko) The musician Sadko becomes a wealthy merchant through the aid of the Water Tsar, but refuses to pay tribute when his ships pass over the sea. His fleet is becalmed, and after casting lots Sadko is forced to give himself to the sea to save his sailors. Sadko is brought before the Water Tsar and Tsarina to settle an argument: Which is more valuable in Novgorod above, iron or gold? Sadko explains that iron is more valuable because it is necessary for daily life, enraging the Water Tsar. Sadko calms the Tsar by playing his gusli, but the Tsar\u2019s wild dancing thrashes the oceans, causing many ships to be smashed upon the sea. \u2588\u2588\u2588\u2588\u2588\u2588\u2588\u2588\u2588\u2588\u2588\u2588\u2588 \u2588\u2588\u2588\u2588\u2588\u2588\u2588\u2588\u2588\u2588\u2588\u2588\u2588\u2588\u2588\u2588\u2588\u2588\u2588\u2588\u2588\u2588\u2588\u2588\u2588\u2588\u2588\u2588\u2588\u2588\u2588\u2588\u2588\u2588\u2588\u2588\u2588\u2588\u2588\u2588\u2588\u2588\u2588\u2588\u2588\u2588\u2588\u2588\u2588\u2588\u2588\u2588\u2588\u2588\u2588\u2588\u2588\u2588\u2588\u2588\u2588\u2588\u2588 \u2588\u2588\u2588\u2588\u2588\u2588\u2588\u2588\u2588\u2588\u2588\u2588\u2588\u2588\u2588\u2588\u2588\u2588\u2588\u2588\u2588\u2588\u2588\u2588\u2588\u2588\u2588\u2588\u2588\u2588\u2588\u2588\u2588\u2588\u2588\u2588\u2588\u2588\u2588\u2588\u2588\u2588\u2588\u2588\u2588\u2588\u2588\u2588\u2588\u2588\u2588\u2588\u2588\u2588\u2588\u2588\u2588\u2588\u2588\u2588\u2588\u2588\u2588 \u2588\u2588\u2588\u2588\u2588\u2588\u2588\u2588\u2588\u2588\u2588\u2588\u2588\u2588\u2588\u2588\u2588\u2588\u2588\u2588\u2588\u2588\u2588\u2588\u2588\u2588\u2588\u2588\u2588\u2588\u2588\u2588\u2588\u2588\u2588\u2588\u2588\u2588\u2588\u2588\u2588\u2588\u2588\u2588\u2588\u2588\u2588\u2588\u2588\u2588\u2588\u2588\u2588\u2588\u2588\u2588\u2588\u2588\u2588\u2588\u2588\u2588\u2588 (Page 22/35)",
        "END SELECTED PORTIONS. Full report available from RAISA to personnel with GREAT GAME clearance.",
        "\" SCP-2577 \" by Petrograd, from the SCP Wiki . Source: https://scpwiki.com/scp-2577 . Licensed under CC-BY-SA ."
    ],
    "item": "SCP-2577",
    "object_class": "Euclid",
    "containment_procedures": "Foundation web-crawlers and embedded personnel in the entertainment industry are to monitor for and prevent any distribution of SCP-2577. Copyrights have been registered under Foundation front corporations for this purpose.",
    "description": "SCP-2577 is a 2005 documentary series titled \u201cFrozen Steel\u201d occasionally appearing on streaming video services or small-scale physical media releases. SCP-2577 purportedly documents the operation and daily lives of the staff of SCP-2577-A, a decommissioning yard ostensibly located in \u2588\u2588\u2588\u2588\u2588\u2588\u2588, Siberian Federal District, Russia, used for the disposal of military ships ranging in age from the early to mid-twentieth century. SCP-2577-A consists of a single central command tower and barracks surrounded by a \u2588\u2588 square km runway constructed from level, packed tundra. Ships are delivered to this runway through means never expressed in the documentary, arriving ballistically at speeds exceeding 900\u00a0km/h before violently embedding themselves in the runway.",
    "title": "SCP-2577"
}