{
    "url": "https://scp-wiki.wikidot.com/scp-2755",
    "all_text": "rating:\u00a0\n+112\n+\n\u2013\nx\n\n\nItem #:\n SCP-2755\n\n\nObject Class:\n Safe\n\n\nSpecial Containment Procedures:\n SCP-2755 is to be stored in a standard biological item vault outfitted with a drain for excess fluids.\n\n\nDescription:\n SCP-2755 is the corpse of Finnegan \u2588\u2588\u2588\u2588\u2588, a comedy writer noted for a family-friendly series of joke books, [REDACTED]. The corpse itself is effectively affixed to the couch supporting it. Of particular note is its position; its right hand holds a shot glass under SCP-2755's mouth. Discharging from the mouth at 0.5\u00a0mL/hour is isopropyl alcohol, which drips into the shot glass. When overfilled, and the alcohol reaches a suitable material, most additional alcohol evaporates. The remaining alcohol proceeds to cover the material's surface and etches a random pun from one of the writer's books, as well as a typically cynical addition. See Addendum for transcripts.\n\n\nAddendum A: Transcript of Etchings\n\n\n\n\nWhy did the cow not want to go to school? Because it had recently mooved!\n\n\n\u2026 Just like I did for this shitty job in Loserville, Nowhere.\n\n\n\n\n\n\nHow do dolphins like their soda pop? Bottled!\n\n\nJust like my whiskey, acetaminophen, and rage.\n\n\n\n\n\n\nWhat did the archaeologist say when he accidentally broke an artifact? \"I owe you guys an anthrApology.\"\n\n\n\u2026 I'm sorry. I'm so, so sorry. Forgive me.\n\n\n\n\n\n\n\n\n\u00ab \nSCP-2754\n | SCP-2755 | \nSCP-2756\n \u00bb\n\n\n\n\n\n\n\n\n\n\n\u2021\u00a0Licensing\u00a0/\u00a0Citation\n\n\n\n\n\u2021\u00a0Hide\u00a0Licensing\u00a0/\u00a0Citation\n\n\n\n\nCite this page as:\n\n\n \n\n\n\n\n\"\nSCP-2755\n\" by DolphinSlugchugger, from the \nSCP Wiki\n. Source: \nhttps://scpwiki.com/scp-2755\n. Licensed under \nCC-BY-SA\n.\n\n\n\n\n\n\n\n\nFor information on how to use this component, see the \nLicense Box component\n. To read about licensing policy, see the \nLicensing Guide\n.",
    "addendums": [
        "Addendum A: Transcript of Etchings"
    ],
    "documents": [],
    "notes": [
        "Why did the cow not want to go to school? Because it had recently mooved! \u2026 Just like I did for this shitty job in Loserville, Nowhere.",
        "How do dolphins like their soda pop? Bottled! Just like my whiskey, acetaminophen, and rage.",
        "What did the archaeologist say when he accidentally broke an artifact? \"I owe you guys an anthrApology.\" \u2026 I'm sorry. I'm so, so sorry. Forgive me.",
        "\" SCP-2755 \" by DolphinSlugchugger, from the SCP Wiki . Source: https://scpwiki.com/scp-2755 . Licensed under CC-BY-SA ."
    ],
    "item": "SCP-2755",
    "object_class": "Safe",
    "containment_procedures": "SCP-2755 is to be stored in a standard biological item vault outfitted with a drain for excess fluids.",
    "description": "SCP-2755 is the corpse of Finnegan \u2588\u2588\u2588\u2588\u2588, a comedy writer noted for a family-friendly series of joke books, [REDACTED]. The corpse itself is effectively affixed to the couch supporting it. Of particular note is its position; its right hand holds a shot glass under SCP-2755's mouth. Discharging from the mouth at 0.5\u00a0mL/hour is isopropyl alcohol, which drips into the shot glass. When overfilled, and the alcohol reaches a suitable material, most additional alcohol evaporates. The remaining alcohol proceeds to cover the material's surface and etches a random pun from one of the writer's books, as well as a typically cynical addition. See Addendum for transcripts.",
    "title": "SCP-2755"
}