{
    "url": "https://scp-wiki.wikidot.com/scp-3128",
    "all_text": "rating:\u00a0\n+465\n+\n\u2013\nx\n\n\n\n\n\uf129\n\n\n\n\n\n\n\n\nclose\n\n\n\n\n\n\n\n\nInfo\n\n\n\n\n\n\nX\n\n\n\n\nSCP-3128:\n Let's Play Monopoly!\n\n\nAuthor:\n \nThe Great Hippo\n\n\nImages:\n \nLink\n.\n\n\nMusic:\n \nMonopoly Theme\n (???)\n\n\nNext: [\nSCP-3138\n]: \nA Sepulcher by the Sea\n\n\n\n\n\n\nMore by \nThe Great Hippo\n:\n\n\n\n\nSCPs\n\n\n\n\n\u2013\u00a0hide\u00a0block\n\n\n\n\n\n\n\n\nSCPs\n\n\n\n\n\n\n[\nSCP-3034\n]\n\n\nThe Counting Station\n\n\n\n\n\n\nDO NOT LET HER FINISH\n\n\n\n\n\n\n[\nSCP-3035\n]\n\n\nScience Bugs\n\n\n\n\n\n\ncase_of_the_mondays.png, case_of_the_mondays (1).png\n\n\n\n\n\n\n[\nSCP-3054\n]\n\n\nCragstaff Sanitarium\n\n\n\n\n\n\nYou are sick. You are broken. We will fix you.\n\n\n\n\n\n\n[\nSCP-3045\n]\n\n\nbzzip.exe\n\n\n\n\n\n\nHAMLET: I am no longer moody.\n\n\n\n\n\n\n[\nSCP-3043\n]\n\n\nMurphy Law in\u2026 Type 3043 \u2014 FOR MURDER!\n\n\n\n\n\n\nForget it, Fred. It's Chinatown.\n\n\n\n\n\n\n[\nSCP-3057\n]\n\n\nFossil Fuels\n\n\n\n\n\n\n\u2026witnesses provided confirmation that instances of SCP-3057-4 did, in fact, have feathers.\n\n\n\n\n\n\n[\nSCP-2639\n]\n\n\nVideo Game Violence\n\n\n\n\n\n\ni need to know how many people i've killed\n\n\n\n\n\n\n[\nSCP-437\n]\n\n\nSummer of '91\n\n\n\n\n\n\nThat was a pretty crazy summer, y'know? Sometimes I really miss that place.\n\n\n\n\n\n\n[\nSCP-3079\n]\n\n\n300 Tricks: Stage Magic Made Easy\n\n\n\n\n\n\nNOTE:\n No method for accomplishing this trick is provided.\n\n\n\n\n\n\n[\nSCP-2753\n]\n\n\nLet's Play Jenga!\n\n\n\n\n\n\nHigh art carries high risk!\n\n\n\n\n\n\n[\nSCP-2679\n]\n\n\nThe Many Graves of Jeannette Parslov\n\n\n\n\n\n\nWhatever it takes, do what you must; whatever the cost, come back to us.\n\n\n\n\n\n\n[\nSCP-3074\n]\n\n\nKafka's Parking Garage\n\n\n\n\n\n\nThank you for choosing Izatova Parking Center. Have a pleasant day.\n\n\n\n\n\n\n[\nSCP-2571\n]\n\n\nCragglewood Park\n\n\n\n\n\n\nMr. Blair, have you always been an only child?\n\n\n\n\n\n\n[\nSCP-2419\n]\n\n\nThe Laughing Men\n\n\n\n\n\n\nThrow them back into the incinerator where you found them.\n\n\n\n\n\n\n[\nSCP-3143\n]\n\n\nMurphy Law in\u2026 The Foundation Always Rings Twice!\n\n\n\n\n\n\nWhen it comes right down to it, me \u2014 them \u2014 hell, even you \u2014 we're all just characters in that trashy dime-store novel called life.\n\n\n\n\n\n\n[\nSCP-3089\n]\n\n\nThat Old Time Religion\n\n\n\n\n\n\nRemember how we explained that successful people don't actually need any of their toes to walk? Well, that's going to come in handy for Secret Number Six.\n\n\n\n\n\n\n[\nSCP-3117\n]\n\n\nA Monster-Shaped Hole\n\n\n\n\n\n\nI'm not talking to you.\n\n\n\n\n\n\n[\nSCP-3128\n]\n\n\nLet's Play Monopoly!\n\n\n\n\n\n\nHey, guys? I'm, uh. I'm using this.\n\n\n\n\n\n\n[\nSCP-3138\n]\n\n\nA Sepulcher by the Sea\n\n\n\n\n\n\nShould it prove feasible, all non-canonical corpses are to be extracted, examined, and catalogued.\n\n\n\n\n\n\n[\nSCP-3241\n]\n\n\nThe SS Sommerfeld\n\n\n\n\n\n\nIt makes me wonder what an old monster like myself is even doing here, anymore. And then? Someone special comes along and reminds me.\n\n\n\n\n\n\n[\nSCP-3219\n]\n\n\nThis Sour Earth\n\n\n\n\n\n\nNotably, no reports describe any attempt to examine the residence's storm cellar.\n\n\n\n\n\n\n[\nSCP-4028\n]\n\n\nLa Historia de Don Quixote de la Mancha\n\n\n\n\n\n\nJustine eventually re-unites with her sister, Juliette. Alonso strikes down a lightning bolt intended for them both, then challenges the narrator to a duel.\n\n\n\n\n\n\n[\nSCP-3546\n]\n\n\nDoggone it, I Fold!\n\n\n\n\n\n\nSpecifically, fan-art of Sonic the Hedgehog, a video-game character produced by Sega in 1991.\n\n\n\n\n\n\n[\nSCP-3561\n]\n\n\nAn Unfinished Work\n\n\n\n\n\n\nDespite multiple reports from neighbors who claimed to have witnessed members of his family standing at the windows, no trace of Theodore Holdstock's wife and children could be found.\n\n\n\n\n\n\n[\nSCP-4054\n]\n\n\nThe Seventh Door\n\n\n\n\n\n\nSCP-4054 is The Seventh Door, an unlicensed platform adventure game released for the Nintendo Entertainment System in 1988.\n\n\n\n\n\n\n\n\n\n\n\n\n\n\n\n\n\n\n\n\nrating:\u00a0\n+465\n+\n\u2013\nx\n\n\n\n\n\n\n\n\n\n\n\n\n\n\n\n\n\n\n\n\nSCP-3128.\n\n\n\n\n\n\nItem #:\n SCP-3128\n\n\nObject Class:\n Safe\n\n\nSpecial Containment Procedures:\n SCP-3128 is to be kept in a secured locker on-site. Access is limited to Level-4 personnel; following Incident 3128-073, testing is prohibited.\n\n\nMTF Iota-10 (\"Damn Feds\") is to work with law enforcement personnel to investigate the whereabouts of PoI-3128-1. If found, she is to be apprehended and taken into Foundation custody.\n\n\nDescription:\n SCP-3128 is a near-complete Monop\u00f3lio\n1\n game-set originally produced in Portugal at some point in 1937. When played, it exerts an anomalous effect upon global real estate markets; events in reality will mirror events in the game. Following the subprime mortgage crisis of 2007, all further tests by researchers involving manipulation of real estate markets via game-play have been suspended.\n\n\nFollowing Incident 3128-073, all testing is suspended pending review.\n\n\nAddendum 3128.1:\n Incident Log\n\n\n\n\n\u25ba\u00a0ACCESS\u00a0SCP:/3128/incidents/073.log\n\n\n\n\n\u25bc\u00a0Close\u00a0File\n\n\n\n\n\n\nINCIDENT LOG\n\n\n\n\nDATE:\n 09/21/2009\n\n\nPARTICIPANTs:\n D-3128-1 (ALPHA), D-3128-2 (BETA), D-3128-3 (GAMMA)\n\n\nSUBJECT:\n SCP-3128\n\n\nNOTES:\n The following is an excerpt from the audio taken during a test.\n\n\n\n\n[\nBEGIN LOG.\n]\n\n\nALPHA:\n It's your turn.\n\n\nGAMMA:\n Fuck.\n\n\nALPHA:\n C'mon, roll.\n\n\nGAMMA:\n There's no way I can win. You've already got, like, six complete monopolies, man.\n\n\nBETA:\n Just roll.\n\n\nGAMMA:\n Fine, whatever. I always hated this stupid \u2014\n\n\n[\nDice rolling.\n]\n\n\nBETA:\n Take your 'Chance' card.\n\n\nGAMMA:\n Yeah.\n\n\n[\nSilence.\n]\n\n\nALPHA:\n Well?\n\n\n[\nSilence.\n]\n\n\nALPHA:\n What is it?\n\n\nGAMMA:\n Uh. One sec. Need to \u2014 uh, I need to try something.\n\n\n[\nShuffling.\n]\n\n\n[\nKnocking.\n]\n\n\nBETA:\n What the hell are you \u2014\n\n\nGAMMA:\n Hey, guys? I'm, uh. I'm using this.\n\n\nBETA:\n \u2014 the hell are you doing?\n\n\n[\nDoor opening.\n]\n\n\nALPHA:\n What the \u2014\n\n\nGAMMA:\n Good luck, you two.\n\n\nBETA:\n How are you \u2014 where are you \u2014\n\n\n[\nDoor closing.\n]\n\n\n[\nEND LOG.\n]\n\n\n\n\nNOTE:\n D-3128-3 has been designated as PoI-3128-1. Documentation of SCP-3128 updated to note several pieces are now missing; this includes one of its 'Get Out Of Jail Free' cards.\n\n\n\n\n\n\n\n\n\n\n\n\nFootnotes\n\n\n1\n. Otherwise known as 'Monopoly' in the US and UK.\n\n\n\n\n\n\n\n\n\u00ab \nSCP-3127\n | SCP-3128 | \nSCP-3129\n \u00bb\n\n\n\n\n\n\n\n\n\n\n\u2021\u00a0Licensing\u00a0/\u00a0Citation\n\n\n\n\n\u2021\u00a0Hide\u00a0Licensing\u00a0/\u00a0Citation\n\n\n\n\nCite this page as:\n\n\n \n\n\n\n\n\"\nSCP-3128\n\" by The Great Hippo, from the \nSCP Wiki\n. Source: \nhttps://scpwiki.com/scp-3128\n. Licensed under \nCC-BY-SA\n.\n\n\n\n\n\n\n\n\nFor information on how to use this component, see the \nLicense Box component\n. To read about licensing policy, see the \nLicensing Guide\n.\n\n\n\n\n\n\nFilename:\n monopolio2.jpg\n\n\nName:\n 2007-150-656 (15406600117).jpg\n\n\nAuthor:\n \nStudio Alijn\n\n\nLicense:\n Public Domain\n\n\nSource Link:\nWikimedia",
    "addendums": [
        "Addendum 3128.1: Incident Log"
    ],
    "documents": [],
    "notes": [
        "INCIDENT LOG DATE: 09/21/2009 PARTICIPANTs: D-3128-1 (ALPHA), D-3128-2 (BETA), D-3128-3 (GAMMA) SUBJECT: SCP-3128 NOTES: The following is an excerpt from the audio taken during a test. [ BEGIN LOG. ] ALPHA: It's your turn. GAMMA: Fuck. ALPHA: C'mon, roll. GAMMA: There's no way I can win. You've already got, like, six complete monopolies, man. BETA: Just roll. GAMMA: Fine, whatever. I always hated this stupid \u2014 [ Dice rolling. ] BETA: Take your 'Chance' card. GAMMA: Yeah. [ Silence. ] ALPHA: Well? [ Silence. ] ALPHA: What is it? GAMMA: Uh. One sec. Need to \u2014 uh, I need to try something. [ Shuffling. ] [ Knocking. ] BETA: What the hell are you \u2014 GAMMA: Hey, guys? I'm, uh. I'm using this. BETA: \u2014 the hell are you doing? [ Door opening. ] ALPHA: What the \u2014 GAMMA: Good luck, you two. BETA: How are you \u2014 where are you \u2014 [ Door closing. ] [ END LOG. ] NOTE: D-3128-3 has been designated as PoI-3128-1. Documentation of SCP-3128 updated to note several pieces are now missing; this includes one of its 'Get Out Of Jail Free' cards.",
        "\" SCP-3128 \" by The Great Hippo, from the SCP Wiki . Source: https://scpwiki.com/scp-3128 . Licensed under CC-BY-SA .",
        "Filename: monopolio2.jpg Name: 2007-150-656 (15406600117).jpg Author: Studio Alijn License: Public Domain Source Link: Wikimedia"
    ],
    "item": "SCP-3128",
    "object_class": "Safe",
    "containment_procedures": "SCP-3128 is to be kept in a secured locker on-site. Access is limited to Level-4 personnel; following Incident 3128-073, testing is prohibited.",
    "description": "SCP-3128 is a near-complete Monop\u00f3lio1 game-set originally produced in Portugal at some point in 1937. When played, it exerts an anomalous effect upon global real estate markets; events in reality will mirror events in the game. Following the subprime mortgage crisis of 2007, all further tests by researchers involving manipulation of real estate markets via game-play have been suspended.",
    "title": "SCP-3128"
}