{
    "url": "https://scp-wiki.wikidot.com/scp-4880",
    "all_text": "rating:\u00a0\n+70\n+\n\u2013\nx\n\n\n\n\n\n\nSCP-4880, unwrapped.\n\n\n\n\n\n\nItem #:\n SCP-4880\n\n\nObject Class:\n Safe\n\n\nSpecial Containment Procedures:\n SCP-4880 is kept inside its container in a low security containment locker at \nSite-98\n. No other containment procedures are necessary.\n\n\nSCP-4880-1 is to be contained within the area of its location with a security perimeter. This perimeter is to take the form of a barbed wire fence with two guards for maintenance.\n\n\nDescription:\n SCP-4880 appears to be a stack of ten ordinary chewing gum sticks labelled \"Chewin' Gum!\". SCP-4880 does not appear physically anomalous other than the effect it has on sapient entities and the lack of a nutrition facts label.\n\n\nWhen SCP-4880 is chewed, the person affected will begin to proclaim how SCP-4880 is an appealing product and how delicious or sweet it is, in an attempt to advertise it to others nearby\n1\n. Towards the end of the message, the person advertising SCP-4880 will hold it, and finish the speech by saying \"Try one now, and get chewing!\" before spontaneously vanishing.\n\n\nSCP-4880-1 is a large, dilating mass of polymers, plasticizers, and humanoid entities covered in a thin layer of human saliva. SCP-4880-1 was discovered in an abandoned steel mill factory in the Odda municipality of Hordaland county, Norway, after a tracker was placed around the wrist of a D-Class (D-11122) to recover where these individuals disappear to after ingesting SCP-4880. One of the hands of SCP-4880-1 was wearing this tracker.\n\n\nSCP-4880-1 frequently moves parts of the bodies attached to its mass but at a slowed pace. The entities that appear within this mass are tightly constricted under the layer and have been shown to undergo labored breathing. Vocalizations can be heard from the mouths of these entities which always consists of low gurgling noises and continuing to advertise SCP-4880.\n\n\nAddendum 4880.1:\n Attached is the product description found on SCP-4880.\n\n\n\n\nAccess\u00a0File\n\n\n\n\nClose\u00a0File\n\n\n\n\n\n\n\n\nGET CHEWING!\n\n\n\n\nThe new and latest product from \nSugarcomb Confections\n: \nChewin' Gum!\n\nIf you've tried our delicious chocolates and our \nother sweet\n \nsurprises\n, you're in for a tasty treat with this!\n\nStart the day right with sweet, sweet, suh-weet gum!\n\nAnd remember kids: Don't forget to brush your teeth!\n\n~ Oliver\n\n\n\n\n\n\n\n\n\n\n\n\nAddendum 4880.2:\n Recovered Note\n\nThe following file contains a note recovered near a pile of ash nearby the location of SCP-4880-1. The upper portion is burnt with only the lower half being readable.\n\n\n\n\nAccess\u00a0File\n\n\n\n\nClose\u00a0File\n\n\n\n\n\n\nI don't care how you get rid of them, just dump it somewhere else.\n\n\nFix it or else it's your head.\n\n\n- Ollie\n\n\n\n\n\n\n\n\n\n\n\n\nFootnotes\n\n\n1\n. This effect also occurs if the individual is alone.\n\n\n\n\n\n\n\n\n\u00ab \nSCP-4879\n | SCP-4880 | \nSCP-4881\n \u00bb",
    "addendums": [
        "Addendum 4880.1: Attached is the product description found on SCP-4880.",
        "Addendum 4880.2: Recovered Note The following file contains a note recovered near a pile of ash nearby the location of SCP-4880-1. The upper portion is burnt with only the lower half being readable."
    ],
    "documents": [],
    "notes": [
        "GET CHEWING! The new and latest product from Sugarcomb Confections : Chewin' Gum! If you've tried our delicious chocolates and our other sweet surprises , you're in for a tasty treat with this! Start the day right with sweet, sweet, suh-weet gum! And remember kids: Don't forget to brush your teeth! ~ Oliver",
        "I don't care how you get rid of them, just dump it somewhere else. Fix it or else it's your head. - Ollie"
    ],
    "item": "SCP-4880",
    "object_class": "Safe",
    "containment_procedures": "SCP-4880 is kept inside its container in a low security containment locker at Site-98. No other containment procedures are necessary.",
    "description": "SCP-4880 appears to be a stack of ten ordinary chewing gum sticks labelled \"Chewin' Gum!\". SCP-4880 does not appear physically anomalous other than the effect it has on sapient entities and the lack of a nutrition facts label.",
    "title": "SCP-4880"
}