{
    "url": "https://scp-wiki.wikidot.com/scp-4939",
    "all_text": "rating:\u00a0\n+73\n+\n\u2013\nx\n\n\n \n\n\nItem #:\n SCP-4939\n\n\nObject Class:\n Safe\n\n\nSpecial Containment Procedures:\n SCP-4939 is self-containing within its documentation file.\n\n\nDescription:\n SCP-4939 is an anomalous error within the Foundation database attached to the statement listed below.\n\n\nUpon clicking an individual word in the statement below, the subject will be redirected to a series of Foundation documents, the majority of which seemingly belong to an alternate timeline, i.e. documentation of undiscovered anomalies.\n\n\nSCP-4939:\n\n\n \n\n\n\n\nA\n \nstarlight\n \ndance\n.\n\n\n\n\n\n\n\n\n\n\n\n\n\u00ab \nSCP-4938\n | SCP-4939 | \nSCP-4940\n \u00bb",
    "addendums": [],
    "documents": [],
    "notes": [
        "A starlight dance ."
    ],
    "item": "SCP-4939",
    "object_class": "Safe",
    "containment_procedures": "SCP-4939 is self-containing within its documentation file.",
    "description": "SCP-4939 is an anomalous error within the Foundation database attached to the statement listed below.",
    "title": "SCP-4939"
}