{
    "url": "https://scp-wiki.wikidot.com/scp-5011",
    "all_text": "rating:\u00a0\n+169\n+\n\u2013\nx\n\n\n\n\nLIVING ARCHIVE DOCUMENT: LEVEL 4 SECURITY CLEARANCE REQUIRED\n\n\nThe following documentation is curated by Chief Archivist Bridge. It is still considered an active security breach and as such has received perpetual exemption from -ARC or -EX reclassification. This will be reviewed in the event of SCP-5011's cultural significance diminishing.\n\n\n\n\n\n\n\u2026The veil between light and dark is very thin, barely translucent. A pair of eyes glimpsing what\u2019s really on the other side can alter the course of history.\n\n\n\u2014 Bridge, D. (Archivist) \nKeynote Address, Foundation Information Security Conference (FISC).\n Site-19: FISC Conference Series\n\n\n\n\n[Input\u00a0SCP-5011\u00a0Access\u00a0Credentials]\n\n\n\n\n[Welcome,\u00a0Director\u00a0Bridge]\n\n\n\n\n\n\nItem #:\n SCP-5011\n\n\nObject Class:\n N/A\n\n\nSpecial Containment Procedures:\n N/A\n\n\nDescription:\n SCP-5011 designates the consequences of an information leak regarding an anomalous being. This occurred under the stewardship of the American Secure Containment Initiative. The anomaly itself was decommissioned as part of the absorption of the ASCI into the SCP Foundation.\n\n\nFirst appearance of SCP-5011 cultural contamination\n\n\n\n\n\n\n\n\n\n\n\n\n\n\n\n\n\n\n\n\n\n\n\n\n\n\n\n\n\n\n\n\n\n\n\n\n\u00ab \nSCP-5010\n | SCP-5011 | \nSCP-5012\n \u00bb\n\n\n\n\n\n\n\n\n\n\n\u2021\u00a0Licensing\u00a0/\u00a0Citation\n\n\n\n\n\u2021\u00a0Hide\u00a0Licensing\u00a0/\u00a0Citation\n\n\n\n\nCite this page as:\n\n\n \n\n\n\n\n\"\nSCP-5011\n\" by Anonymous, jinjja, from the \nSCP Wiki\n. Source: \nhttps://scpwiki.com/scp-5011\n. Licensed under \nCC-BY-SA\n.\n\n\n\n\n\n\n\n\nFor information on how to use this component, see the \nLicense Box component\n. To read about licensing policy, see the \nLicensing Guide\n.\n\n\n\n\n\n\nFilename:\n page1, page2, page3, page4, page5, page6, page7, page8, page9, page10\n\n\nAuthor:\n Anonymous & \njinjja\n\n\nLicense:\n CC BY-SA 3.0\n\n\nSource Link:\n \nSCP Foundation Wiki\n\n\n\n\n\n\nFilename:\n Reign\n\n\nName:\n Reign of the Superman.jpg\n\n\nAuthor:\n Herbert S. Fine\n\n\nLicense:\n Public Domain\n\n\nSource Link:\n \nWikimedia Commons",
    "addendums": [],
    "documents": [],
    "notes": [
        "\" SCP-5011 \" by Anonymous, jinjja, from the SCP Wiki . Source: https://scpwiki.com/scp-5011 . Licensed under CC-BY-SA .",
        "Filename: page1, page2, page3, page4, page5, page6, page7, page8, page9, page10 Author: Anonymous & jinjja License: CC BY-SA 3.0 Source Link: SCP Foundation Wiki",
        "Filename: Reign Name: Reign of the Superman.jpg Author: Herbert S. Fine License: Public Domain Source Link: Wikimedia Commons"
    ],
    "item": "SCP-5011",
    "object_class": "N/A",
    "containment_procedures": "N/A",
    "description": "SCP-5011 designates the consequences of an information leak regarding an anomalous being. This occurred under the stewardship of the American Secure Containment Initiative. The anomaly itself was decommissioned as part of the absorption of the ASCI into the SCP Foundation.",
    "title": "SCP-5011"
}