{
    "url": "https://scp-wiki.wikidot.com/scp-5429",
    "all_text": "rating:\u00a0\n+47\n+\n\u2013\nx\n\n\n\n\nThe following file depicts a recently discovered anomaly, and therefore may have inconsistencies and/or a lack of information.\n\n\n\n\n \n\n\nItem #:\n SCP-5429\n\n\nObject Class:\n Safe\n\n\nSpecial Containment Procedures:\n SCP-5429 is held in a standard humanoid chamber.\n\n\nAn investigation into the nature of SCP-5429 is underway.\n\n\nDescription:\n SCP-5429 is former Senior Researcher Jason Vatili of Site-72's Alchemy Department Wing. Theoretically, when a portion of SCP-5429 is dismembered, a new growth will appear as if the injury never occurred. This effect is yet to be directly observed and thus can not be confirmed as of writing.\n\n\nNotably, a buildup of flesh can be seen bulging from around SCP-5429's shoulder and upper arm. Though it was once a prominent researcher, it is now barely capable of advanced thought nor is it able to hold conversations. SCP-5429 is unable to recall any of its memories prior to 17/03/2021\n1\n.\n\n\nAddendum:\n \nDiscovery and Containment\n\n\nPrior to discovery, an unrelated containment breach occurred at Site-72. Though the anomaly was a Safe Class and there were no deaths, minor structural damage led to SCP-5429's left arm being dismembered from its body. Emergency surgery to reattach the arm was unsuccessful.\n\n\nThe dismembered limb was placed in cold storage per SCP-5429's request, which was to be used for any containment procedures requiring human flesh.\n\n\nThe following day, however, SCP-5429 returned to Site-72 with both arms intact. SCP-5429 was immediately detained and moved to the Safe Containment Sector. Investigation of SCP-5429's residence took place shortly thereafter. Blood, mucus and torn organ tissue had been spread throughout the home. Furniture and belongings were discovered in a state of disarray.\n\n\nAt the same time, the limb was reported missing from cold storage. The following message was found scratched from within its freezer unit:\n\n\n\n\n\n\narm back you \u2014 one only. space no two \u2014 bye\n\n\n\n\n\n\nThe limb is yet to be located.\n\n\n\n\nMore by this author\n\n\n\n\n\n\nFootnotes\n\n\n1\n. The day that SCP-5429 was discovered and contained.\n\n\n\n\n\n\n\n\n\u00ab \nSCP-5428\n | SCP-5429 | \nSCP-5430\n \u00bb\n\n\n\n\n\n\n\n\n\n\n\u2021\u00a0Licensing\u00a0/\u00a0Citation\n\n\n\n\n\u2021\u00a0Hide\u00a0Licensing\u00a0/\u00a0Citation\n\n\n\n\nCite this page as:\n\n\n \n\n\n\n\n\"\nSCP-5429\n\" by SketchyTh0ughts, from the \nSCP Wiki\n. Source: \nhttps://scpwiki.com/scp-5429\n. Licensed under \nCC-BY-SA\n.\n\n\n\n\n\n\n\n\nFor information on how to use this component, see the \nLicense Box component\n. To read about licensing policy, see the \nLicensing Guide\n.",
    "addendums": [
        "Addendum: Discovery and Containment\nPrior to discovery, an unrelated containment breach occurred at Site-72. Though the anomaly was a Safe Class and there were no deaths, minor structural damage led to SCP-5429's left arm being dismembered from its body. Emergency surgery to reattach the arm was unsuccessful.\nThe dismembered limb was placed in cold storage per SCP-5429's request, which was to be used for any containment procedures requiring human flesh.\nThe following day, however, SCP-5429 returned to Site-72 with both arms intact. SCP-5429 was immediately detained and moved to the Safe Containment Sector. Investigation of SCP-5429's residence took place shortly thereafter. Blood, mucus and torn organ tissue had been spread throughout the home. Furniture and belongings were discovered in a state of disarray.\nAt the same time, the limb was reported missing from cold storage. The following message was found scratched from within its freezer unit:\nThe limb is yet to be located."
    ],
    "documents": [],
    "notes": [
        "The following file depicts a recently discovered anomaly, and therefore may have inconsistencies and/or a lack of information.",
        "arm back you \u2014 one only. space no two \u2014 bye",
        "\" SCP-5429 \" by SketchyTh0ughts, from the SCP Wiki . Source: https://scpwiki.com/scp-5429 . Licensed under CC-BY-SA ."
    ],
    "item": "SCP-5429",
    "object_class": "Safe",
    "containment_procedures": "SCP-5429 is held in a standard humanoid chamber.",
    "description": "SCP-5429 is former Senior Researcher Jason Vatili of Site-72's Alchemy Department Wing. Theoretically, when a portion of SCP-5429 is dismembered, a new growth will appear as if the injury never occurred. This effect is yet to be directly observed and thus can not be confirmed as of writing.",
    "title": "SCP-5429"
}