{
    "url": "https://scp-wiki.wikidot.com/scp-5884",
    "all_text": "Are you alive?\n\n\n\n\n\n\n\n\n\n\n[[iftags +component]]\n\n\n\n\nThis is a component to make the mobile sidebar button active on desktop-size screen.\n\nTo use, put the following:\n\n\n\n\n[[include :scp-wiki:component:toggle-sidebar]]\n\n\n\n\nIf used with a theme, it's recommended to put said theme after this \n[[include]]\n.\n\n\n(Use \nthis version\n by \nWoedenaz\n if you're using Black Highlighter)\n\n\n\n\n\n\n\n\n\n\n/\n*\n source: \nhttp\n://\nah-sandbox.wikidot.com\n/\ncomponent\n:collapsible-sidebar-x1\n \n*\n/\n \n\n#top-bar\n \n.open-menu\n \na\n \n{\n\n        \nposition:\n \nfixed\n;\n        \ntop:\n \n0.5\nem\n;\n        \nleft:\n \n0.5\nem\n;\n        \nz-index:\n \n5\n;\n        \nfont-family:\n 'Lucida Sans Unicode','Lucida Grande','Lucida Sans','Times New Roman',Helvetica,Roboto,\nsans-serif\n;\n        \nfont-size:\n \n30\npx\n;\n        \nfont-weight:\n \n700\n;\n        \nwidth:\n \n30\npx\n;\n        \nheight:\n \n30\npx\n;\n        \nline-height:\n \n0.9\nem\n;\n        \ntext-align:\n \ncenter\n;\n        \nborder:\n \n0.2\nem\n \nsolid\n \n#888\n;\n        \nbackground-color:\n \n#fff\n;\n        \nborder-radius:\n \n3\nem\n;\n        \ncolor:\n \n#888\n;\n        \npointer-events:\n \nauto\n;\n\n}\n\n \n\n@media\n \nnot\n \nall\n \nand\n (max-width: 767\npx\n) \n{\n\n \n    \n#top-bar\n \n.mobile-top-bar\n \n{\n\n        \ndisplay:\n \nblock\n;\n        \npointer-events:\n \nnone\n;\n    \n}\n\n \n    \n#top-bar\n \n.mobile-top-bar\n \nli\n \n{\n\n        \ndisplay:\n \nnone\n;\n    \n}\n\n \n    \n#main-content\n \n{\n\n        \nmax-width:\n \n44.5\nrem\n;\n        \nmargin:\n \n0\n \nauto\n;\n        \npadding:\n \n0\n;\n        \ntransition:\n max-width \n0.2\ns ease-in-out\n;\n    \n}\n\n \n    \n#side-bar\n \n{\n\n        \ndisplay:\n \nblock\n;\n        \nposition:\n \nfixed\n;\n        \ntop:\n \n0\n;\n        \nleft:\n -\n18\nrem\n;\n        \nwidth:\n \n15.25\nrem\n;\n        \nheight:\n \n100\n%\n;\n        \nmargin:\n \n0\n;\n        \noverflow-x:\n \nhidden\n;\n        \noverflow-y:\n \nauto\n;\n        \nz-index:\n \n10\n;\n        \npadding:\n \n1\nem\n \n1\nem\n \n0\n \n1\nem\n;\n        \nbackground-color:\n rgba(\n0\n,\n0\n,\n0\n,\n0.1\n)\n;\n        \ntransition:\n \nleft\n \n0.4\ns ease-in-out\n;\n \n        \nscrollbar-width:\n \nthin\n;\n    \n}\n\n \n    \n#side-bar\n:\ntarget\n \n{\n\n        \nleft:\n \n0\n;\n    \n}\n\n    \n#side-bar\n:\nfocus-within\n \n{\n\n        \nleft:\n \n0\n;\n    \n}\n\n \n    \n#side-bar\n:\ntarget\n \n.close-menu\n \n{\n\n        \ndisplay:\n \nblock\n;\n        \nposition:\n \nfixed\n;\n        \nwidth:\n \n100\n%\n;\n        \nheight:\n \n100\n%\n;\n        \ntop:\n \n0\n;\n        \nleft:\n \n0\n;\n        \nmargin-left:\n \n17\nrem\n;\n        \nopacity:\n \n0\n;\n        \nz-index:\n -\n1\n;\n        \nvisibility:\n \nvisible\n;\n    \n}\n\n    \n#side-bar\n:\nnot\n(:\ntarget\n) \n.close-menu\n \n{\n \ndisplay:\n \nnone\n; \n}\n\n \n    \n#top-bar\n \n.open-menu\n \na:\nhover {\n        text-decoration: \nnone\n;\n    \n}\n\n}\n\n\n\n\n\n[[/iftags]]\n\n\n\n\nrating:\u00a0\n+23\n+\n\u2013\nx\n\n\nItem #:\n SCP-5884\n\n\nObject Class:\n Keter\n\n\nSpecial Containment Procedures:\n In order to neutralize SCP-5884, the following actions have been authorized:\n\n\n\n\nMobilization of all available Task Forces to major population centers\n\n\nDecommissioning of \nSCP-4043\n\n\nCessation of contact with \nthe Three Moons Initiative\n\n\nSpreading vectors of \nSCP-3002\n\n\nDeactivation of \nSCP-2935\n's containment\n\n\nProject Serapis II\n\n\nSCP-3980\n\n\n\n\nShould the aforementioned actions fail to stop SCP-5884, all remaining unaffected personnel is to neither live nor die until further notice.\n\n\nDescription:\n SCP-5884 is a currently poorly-understood mechanism that was activated on 2021/06/30, intrinsically tied to 'the ensured survival of humanity.'\n\n\n\n\nThe effects of SCP-5884 manifested when\n\n\n\n\n \n\n\n \n\n\n \n\n\n \n\n\n \n\n\n \n\n\n \n\n\n \n\n\n \n\n\n \n\n\n \n\n\n \n\n\n \n\n\n \n\n\n \n\n\n \n\n\n \n\n\n \n\n\n \n\n\n \n\n\n \n\n\n \n\n\n \n\n\n \n\n\n \n\n\n \n\n\n \n\n\n \n\n\n \n\n\n \n\n\n \n\n\n \n\n\n \n\n\n \n\n\n \n\n\n \n\n\n \n\n\n \n\n\n \n\n\n \n\n\n \n\n\n \n\n\n \n\n\n \n\n\n \n\n\n \n\n\n \n\n\n \n\n\n \n\n\n \n\n\n \n\n\n \n\n\n \n\n\n \n\n\n \n\n\n\n\nNew\u00a0file\u00a0uploaded.\u00a0Open?\n\n\n\n\nOpening...\n\n\n\n\n\n\n(Video log - 2021/07/01)\n\n\n(O5-1 sits motionless in the middle of the room.)\n1\n\n\n(This continues for 4 minutes, until he turns to his right to look at a pistol.)\n\n\n(O5-1 grabs the pistol, and examines it for 2 minutes.)\n\n\n(He slowly points it at his temple, and mouths 'I need to know.')\n\n\n \n\n\n(O5-1 pulls the trigger.)\n\n\n \n\n\n(The bullet exits through the other side of O5-1's skull, splattering blood and brain particulates onto the wall.)\n\n\n(O5-1 lives immediately, and becomes human.)\n\n\n \n\n\n \n\n\n(O5-1 sits up, and remains still for 4 more minutes.)\n\n\n \n\n\n(He wipes his head clean of blood, and leaves the room.)\n\n\n\n\n\n\n\n\n\n\n\n\n\n\nFootnotes\n\n\n1\n. O5-1 was dead at the time of recording.\n\n\n\n\n\n\n \n\n\n \n\n\n \n\n\n \n\n\n \n\n\n \n\n\n \n\n\n \n\n\n \n\n\n \n\n\n \n\n\n \n\n\n\n\n\n\n\u00ab \nSCP-5883\n | SCP-5884 | \nSCP-5885\n \u00bb\n\n\n\n\n\n\n\n\n\n\n\u2021\u00a0Licensing\u00a0/\u00a0Citation\n\n\n\n\n\u2021\u00a0Hide\u00a0Licensing\u00a0/\u00a0Citation\n\n\n\n\nCite this page as:\n\n\n \n\n\n\n\n\"\nSCP-5884\n\" by EstrellaYoshte, from the \nSCP Wiki\n. Source: \nhttps://scpwiki.com/scp-5884\n. Licensed under \nCC-BY-SA\n.\n\n\n\n\n\n\n\n\nFor information on how to use this component, see the \nLicense Box component\n. To read about licensing policy, see the \nLicensing Guide\n.",
    "addendums": [],
    "documents": [],
    "notes": [
        "[[include :scp-wiki:component:toggle-sidebar]]",
        "\" SCP-5884 \" by EstrellaYoshte, from the SCP Wiki . Source: https://scpwiki.com/scp-5884 . Licensed under CC-BY-SA ."
    ],
    "item": "SCP-5884",
    "object_class": "Keter",
    "containment_procedures": "In order to neutralize SCP-5884, the following actions have been authorized:",
    "description": "SCP-5884 is a currently poorly-understood mechanism that was activated on 2021/06/30, intrinsically tied to 'the ensured survival of humanity.'",
    "title": "SCP-5884"
}