{
    "url": "https://scp-wiki.wikidot.com/scp-6006",
    "all_text": "rating:\u00a0\n+234\n+\n\u2013\nx\n\n\n \n\n\n\n\n\n\nNOTICE: THIS FILE IS SCHEDULED FOR DELETION\n\n\n\n\nThis containment file is scheduled for deletion in accordance with Foundation procedures regarding Neutralized items. Please do not modify it.\n\n\n\n\n\n\nItem #:\n SCP-6006\n\n\nObject Class:\n Neutralized\n\n\nSpecial Containment Procedures:\n \nPending Deletion, do not modify.\n\n\nSCP-6006 must be contained in a Standard Euclid Containment Chamber, size 7. Due to its infohazardous nature, this containment file must be secured with Level 4 Infohazard Type-A4 encryption.\n\n\nDescription:\n \nRevision of this description is in progress. Do not modify.\n\n\nSCP-6006 is an inert plank measuring 9cm x 7cm x 3m. It appears to be made of \nCupressus sempervirens\n (Mediterranean cypress) wood.\n\n\n\n\n\n\n\n\n\n\n_\n\n\n\n\n\n\nAddendum 6006.A: Foundation Recovery\nAddendum 6006.A: Foundation Recovery\n\n\n\n\n\n\n\u00e2\u20ac\u0161\n\ufffd\n\u8210\ue5f5\ue5f5\ue5f5\u8210 \u00b6????\u255f\u8210\u00a9 \u00c2\u00a3 \u2014\u0158\u00a7\u016e\u255f\u8210 \ue5f5????\ue5f5\ue5f5\ue5f5 \u00f0s\u017e\u0161\u00e5\u00de\u044f\u00a9 \u00bd ????\u2014 \u2014???? \u00e1\u00cd\u00de\u00e6\u00f0s\u017e\u0161\u00e5\u00de\u044f\u00a9\u2014 \u00bb\u8210 \u00a9\u00f0s\u017e\u0161\u00e5\u00de\u044f\ue5f5\ue5f5\ue5f5\u2612\u0158\u00a7\u016e\u2612????\ue5f5\ue5f5\ue5f5\u00a9\n\ufffd\n \u00bb\u00f0s\u017e\u0161\u00e5\u00de\u044f\u2014 \u2014???? \u00bb\u8210 r\u00e1\u00da\u00c6 \u00c2\u00a3\ue5f5\ue5f5\ue5f5\ue5f5\ue5f5\ue5f5\u0158\u00a7\u016e????\ue5f5\ue5f5\ue5f5\u00a9. \u00d3\u00de\u00a2\u00e1\u00f1\u00c2\u00a3\ue5f5\ue5f5\ue5f5\u00c2\u00a3\n\ufffd\n \u00f3\u00de\u00a2\u00e1\u00f1????\u00f0s\u017e\u0161\u00e5\u00de\u044f \u00e2\u20ac\u0161\n\ufffd\n\u00c2\u00a3\u2612\u8210 \u00f3\u00de\u00a2\u00e1\u00f1????\u00f0s\u017e\u0161\u00e5\u00de\u044f\ue5f5\ue5f5\ue5f5 \u00de\u00a5\u00bf\u0158\u00a7\u016e\ue5f5\u8210\n\ufffd\n \u00c2\u00a3\u00bd \u2580 \u2014\u00e2\u20ac\u0161\n\ufffd\n\u8210 \u00b6\u00e2\u20ac\u0161\n\ufffd\n\u00c2\u00a3\u00bd \u00b6\u8210 \u2014???? \u255f\u00c2\u00a3\u0160\u8210 \u2014\u00e2\u20ac\u0161\n\ufffd\n\u8210 \u255f????\u00a9\u2014 ????\ue5f5 \u0158\u00a7\u016e\u2014. \u2580????\u00bd '\u2014 \ue5f5\ue5f5\ue5f5\u00f0s\u017e\u0161\u00e5\u00de\n\n\nThe containment file you are attempting to access encountered an unexpected error. Error code: S7D1010-6000-4252021:A\n\n\n\n\n\n\n\n\n\n\n_\n\n\n\n\n\n\nClick here to launch recovery.\nLaunching recovery manager...\n\n\n\n\n\n\n\n\n\n\nreynholm.aic\n\n\n\n\nWarning. This content does not include any standard validation markers which indicate authoritative Foundation data.\n\n\nAttempts to recover it further should not be made without appropriate infohazard containment protocol in place, as this system cannot determine the contents prior to viewing.\n\n\nProceeding without such clearance may lead to disciplinary action up to and including termination.\n\n\n\n\nProceed\n\n\n\n\n\n\nClose\n\n\n\n\n\n\n\n\nscp.database.decryption.Exception: dumping error log\u2026\n\nat foundation.base/scp.lang.Thread.dumpStack(Thread.scp:1383)\n\nat com.foundation.base.stacktraces.StackTrace.d(StackTrace.scp:23 content was: \"Description\")\n\nat com.foundation.base.stacktraces.StackTrace.c(StackTrace.scp:19 content was: \"I am deleting this so no one else gets hurt\")\n\nat com.foundation.base.stacktraces.StackTrace.b(StackTrace.scp:15 content was: \"Special Containment Protocol\")\n\nat com.foundation.base.stacktraces.StackTrace.a(StackTrace.scp:11 content was: \"SCP-6006\")\n\nat com.foundation.base.stacktraces.StackTrace.main(StackTrace.scp:7 content was null)\n\n\n\n\n\n\n\n\n\n\n\n\n\n\n\n\n\n\n\n\n\n\n\n\n\n\n\n\n\n\n\n\n \n\n\n \n\n\n \n\n\n \n\n\n\n\n\n\n\n\n\n\n\u00ab \nSCP-6005\n | SCP-6006 | \nSCP-6007\n \u00bb\n\n\n\n\n\n\n\n\n\n\n\u2021\u00a0Licensing\u00a0/\u00a0Citation\n\n\n\n\n\u2021\u00a0Hide\u00a0Licensing\u00a0/\u00a0Citation\n\n\n\n\nCite this page as:\n\n\n \n\n\n\n\n\"\nSCP-6006\n\" by Sam Swicegood (CityToast), from the \nSCP Wiki\n. Source: \nhttps://scpwiki.com/scp-6006\n. Licensed under \nCC-BY-SA\n.\n\n\n\n\n\n\n\n\nFor information on how to use this component, see the \nLicense Box component\n. To read about licensing policy, see the \nLicensing Guide\n.\n\n\n\n\n\n\nFilename:\n Ethics_committee_meeting_August_24_1998.jpg\n\n\nAuthor:\n \nCityToast\n\n\nLicense:\n CC BY-SA 3.0\n\n\nSource Link:\n\n\nDerivative of:\n \n787 Battery Fire Investigative Hearing\n by the National Transportation Safety Board, Public Domain\n\n\n\n\n\n\nFilename:\n TWIN_0455.jpg\n\n\nAuthor:\n \nCityToast\n\n\nLicense:\n CC BY-SA 3.0\n\n\nSource Link:\n\n\nDerivative of:\n \nAbandoned Mall\n by Brett Levin, CC BY 2.0\n\n\n\n\n\n\nFilename:\n TWIN_101010.jpg\n\n\nAuthor:\n \nCityToast\n\n\nLicense:\n CC BY-SA 3.0\n\n\nSource Link:\n\n\nDerivative of:\n \nAbandoned Hospital (52)\n by Jan Bommes and \nSightseeing in H\u00f8rsholm's abandoned hospital\n by Manymade, both CC BY-20\n\n\n\n\n\n\nFilename:\n TWIN_74189.jpg\n\n\nAuthor:\n \nCityToast\n\n\nLicense:\n CC BY-SA 3.0\n\n\nSource Link:\n\n\nDerivative of:\n \nAbandoned Hospital\n by Dmitriy Protsenko, CC BY 2.0\n\n\n\n\n\n\nFilename:\n TWIN001.jpg\n\n\nAuthor:\n \nCityToast\n\n\nLicense:\n CC BY-SA 3.0\n\n\nSource Link:\n\n\nDerivative of:\n \nMilf Oven\n by darkday, CC BY 2.0",
    "addendums": [],
    "documents": [],
    "notes": [
        "\" SCP-6006 \" by Sam Swicegood (CityToast), from the SCP Wiki . Source: https://scpwiki.com/scp-6006 . Licensed under CC-BY-SA .",
        "Filename: Ethics_committee_meeting_August_24_1998.jpg Author: CityToast License: CC BY-SA 3.0 Source Link: Derivative of: 787 Battery Fire Investigative Hearing by the National Transportation Safety Board, Public Domain",
        "Filename: TWIN_0455.jpg Author: CityToast License: CC BY-SA 3.0 Source Link: Derivative of: Abandoned Mall by Brett Levin, CC BY 2.0",
        "Filename: TWIN_101010.jpg Author: CityToast License: CC BY-SA 3.0 Source Link: Derivative of: Abandoned Hospital (52) by Jan Bommes and Sightseeing in H\u00f8rsholm's abandoned hospital by Manymade, both CC BY-20",
        "Filename: TWIN_74189.jpg Author: CityToast License: CC BY-SA 3.0 Source Link: Derivative of: Abandoned Hospital by Dmitriy Protsenko, CC BY 2.0",
        "Filename: TWIN001.jpg Author: CityToast License: CC BY-SA 3.0 Source Link: Derivative of: Milf Oven by darkday, CC BY 2.0"
    ],
    "item": "SCP-6006",
    "object_class": "Neutralized",
    "containment_procedures": "Pending Deletion, do not modify.",
    "description": "Revision of this description is in progress. Do not modify.",
    "title": "SCP-6006"
}