{
    "url": "https://scp-wiki.wikidot.com/scp-6612",
    "all_text": "rating:\u00a0\n+157\n+\n\u2013\nx\n\n\nItem #:\n SCP-6612\n\n\n\n\n\n\nSCP-6612 in containment.\n\n\n\n\n\n\nObject Class:\n \nPending\n Neutralized\n\n\nSpecial Containment Procedures:\n SCP-6612 is housed in its original stable within Site-73\u2019s Secure Outdoor Testing Facility. SCP-6612 is to be cleaned and fed daily.\n\n\nDescription:\n SCP-6612 is an adult red roan horse capable of human speech. How SCP-6612 does so is currently unknown.\n\n\nResearch is ongoing.\n\n\nAddendum:\n\n\n\n\nInitial\u00a0Interview\u00a0Log\n\n\n\n\n\u00a0\n\n\n\n\n\n\nInterview Log\n\n\n[BEGIN LOG]\n\n\nResearcher Agnew:\n Hello, SCP-6612.\n\n\nSCP-6612:\n Hi.\n\n\nResearcher Agnew:\n So, you can talk?\n\n\nSCP-6612:\n You heard it straight from the horse\u2019s mouth.\n\n\nSilence for ten seconds\n\n\nSCP-6612:\n This was a mistake.\n\n\n[END LOG]\n\n\n\n\nAddendum:\n SCP-6612 has not spoken again since its initial interview, and has displayed no further attempts to do so.\n\n\nSCP-6612 has been re-classified as Neutralized, and remains in stable condition at Site-73.\n\n\n\n\n\n\n\n\n \n\n\n\n\n\n\n\u00ab \nSCP-6611\n | SCP-6612 | \nSCP-6613\n \u00bb\n\n\n\n\n\n\n\n\n\n\n\u2021\u00a0Licensing\u00a0/\u00a0Citation\n\n\n\n\n\u2021\u00a0Hide\u00a0Licensing\u00a0/\u00a0Citation\n\n\n\n\nCite this page as:\n\n\n \n\n\n\n\n\"\nSCP-6612\n\" by Penton, from the \nSCP Wiki\n. Source: \nhttps://scpwiki.com/scp-6612\n. Licensed under \nCC-BY-SA\n.\n\n\n\n\n\n\n\n\nFor information on how to use this component, see the \nLicense Box component\n. To read about licensing policy, see the \nLicensing Guide\n.\n\n\n\n\n\n\nFilename:\n Red roan horse trotting.jpg\n\n\nAuthor:\n Betty Wills (Atsme)\n\n\nLicense:\n CC BY-SA 4.0\n\n\nSource Link:\n \nWikimedia Commons",
    "addendums": [
        "Addendum:\n"
    ],
    "documents": [],
    "notes": [
        "Interview Log [BEGIN LOG] Researcher Agnew: Hello, SCP-6612. SCP-6612: Hi. Researcher Agnew: So, you can talk? SCP-6612: You heard it straight from the horse\u2019s mouth. Silence for ten seconds SCP-6612: This was a mistake. [END LOG]",
        "\" SCP-6612 \" by Penton, from the SCP Wiki . Source: https://scpwiki.com/scp-6612 . Licensed under CC-BY-SA .",
        "Filename: Red roan horse trotting.jpg Author: Betty Wills (Atsme) License: CC BY-SA 4.0 Source Link: Wikimedia Commons"
    ],
    "item": "SCP-6612",
    "object_class": "Pending Neutralized",
    "containment_procedures": "SCP-6612 is housed in its original stable within Site-73\u2019s Secure Outdoor Testing Facility. SCP-6612 is to be cleaned and fed daily.",
    "description": "SCP-6612 is an adult red roan horse capable of human speech. How SCP-6612 does so is currently unknown.",
    "title": "SCP-6612"
}