{
    "url": "https://scp-wiki.wikidot.com/scp-6742",
    "all_text": "rating:\u00a0\n+104\n+\n\u2013\nx\n\n\nItem #:\n SCP-6742\n\n\nObject Class:\n \nAnomalous\n Pending\n\n\nSpecial Containment Procedures:\n \nSCP-6742 is to be kept in a low-risk anomalous item storage locker at Site-19.\n\n\nSee Addendum-6742-B.\n\n\nDescription:\n SCP-6742 is a black-and-white photograph of a human male, circa early 20th century. The subject is holding a sign that reads \"I'm with the Foundation\". The reverse of the photograph has been marked \"1/17\" with a ballpoint pen.\n\n\nWhen viewed by a Foundation employee, the subject of SCP-6742 will always appear to be looking directly at the viewer. No other anomalous phenomena have been observed during testing.\n\n\nAddendum-6742-A:\n Discovery\n\n\nSCP-6742 was found in a locked box 3 kilometers from Site-01. The contents of the box included a map of the world with several points crossed out, an empty briefcase, and SCP-6742. SCP-6742 was found in a folder containing an additional note, reading \"In case of Foundation takeover, use this to gain their trust.\"\n\n\nAddendum-6742-B:\n Update 17/06/2022\n\n\nBy order of O5-14, testing of SCP-6742 is to be discontinued. Additionally, SCP-6742 has been relocated to an undisclosed location, under the purview of O5-14.\n\n\n\n\n\n\n\u00ab \nSCP-6741\n | SCP-6742 | \nSCP-6743\n \u00bb\n\n\n\n\n\n\n\n\n\n\n\u2021\u00a0Licensing\u00a0/\u00a0Citation\n\n\n\n\n\u2021\u00a0Hide\u00a0Licensing\u00a0/\u00a0Citation\n\n\n\n\nCite this page as:\n\n\n \n\n\n\n\n\"\nSCP-6742\n\" by Fishish, from the \nSCP Wiki\n. Source: \nhttps://scpwiki.com/scp-6742\n. Licensed under \nCC-BY-SA\n.\n\n\n\n\n\n\n\n\nFor information on how to use this component, see the \nLicense Box component\n. To read about licensing policy, see the \nLicensing Guide\n.",
    "addendums": [
        "Addendum-6742-A: Discovery\nSCP-6742 was found in a locked box 3 kilometers from Site-01. The contents of the box included a map of the world with several points crossed out, an empty briefcase, and SCP-6742. SCP-6742 was found in a folder containing an additional note, reading \"In case of Foundation takeover, use this to gain their trust.\"",
        "Addendum-6742-B: Update 17/06/2022\nBy order of O5-14, testing of SCP-6742 is to be discontinued. Additionally, SCP-6742 has been relocated to an undisclosed location, under the purview of O5-14."
    ],
    "documents": [],
    "notes": [
        "\" SCP-6742 \" by Fishish, from the SCP Wiki . Source: https://scpwiki.com/scp-6742 . Licensed under CC-BY-SA ."
    ],
    "item": "SCP-6742",
    "object_class": "Anomalous Pending",
    "containment_procedures": "SCP-6742 is to be kept in a low-risk anomalous item storage locker at Site-19.",
    "description": "SCP-6742 is a black-and-white photograph of a human male, circa early 20th century. The subject is holding a sign that reads \"I'm with the Foundation\". The reverse of the photograph has been marked \"1/17\" with a ballpoint pen.",
    "title": "SCP-6742"
}