{
    "url": "https://scp-wiki.wikidot.com/scp-6911",
    "all_text": "My office is an SCP now. Great.\n\n\n\n\n\n\n\n\n\n\n+\u00a0CODE\n\n\n\n\n-\u00a0CODE\n\n\n\n\n\n\n\n\n\n\n/\n*\n\n    \nBLANKSTYLE\n \nCSS\n\n    \n[\n2021\n \nWikidot\n \nTheme\n]\n\n    \nBy\n \nPlaceholder\n \nMcD\n \nand\n \nHarryBlank\n\n    \nBased\n on:\n       \nPaperstack\n \nTheme\n \nby\n \nEstrellaYoshte\n\n       \nPenumbra\n \nTheme\n \nby\n \nEstrellaYoshte\n\n\n*\n/\n \n\n@import\n \nurl\n('\nhttps\n://\nfonts.googleapis.com\n/\ncss2\n?\nfamily\n=\nMontserrat\n:ital\n,\nwght\n@0\n,800;1,800&\ndisplay\n=\nswap\n');\n \n\n#page-content\n \n{\n \nfont-size:\n \n.9\nrem\n; \n}\n\n \n\n#main-content\n \n{\n\n    \ntop:\n -\n1.6\nrem\n;\n    \npadding:\n \n0.2\nem\n;\n\n}\n\n \n\ndiv#container-wrap\n \n{\n\n     \nbackground-image:\n \nnone\n;\n\n}\n\n \n\ndiv#header\n \n{\n\n    \nbackground-image:\n \nnone\n;\n\n}\n\n \n\n#header\n \nh1\n, \n#header\n \nh2\n \n{\n \nmargin-left:\n \n0\n; \nfloat:\n \nnone\n; \ntext-align:\n \ncenter\n; \n}\n\n\n#header\n \nh2\n \n{\n \nmargin-top:\n \n0.5\nrem\n; \n}\n\n\n#header\n \nh1\n \nspan\n, \n#header\n \nh2\n \nspan\n \n{\n \nfont-size:\n \n0\n; \ndisplay:\n \nnone\n;\n}\n\n\n#header\n \nh1\n \na\n:\n:before\n, \n#header\n \nh2\n:\n:before\n \n{\n\n    \ncolor:\n \n#000\n;\n    \nletter-spacing:\n \n1\npx\n;\n    \nfont-family:\n 'Montserrat', \nsans-serif\n !important\n;\n    \ntext-shadow:\n \nnone\n;\n\n}\n\n \n\n#header\n \nh1\n \na\n:\n:before\n \n{\n\n  \ncontent:\n var(--header-title, \"R\\\n0026\n C SITE-43\")\n;\n  \nfont-weight:\n \n400\n;\n  \nfont-size:\n \n1.3\nem\n;\n\n}\n\n \n\n#header\n \nh2\n:\n:before\n \n{\n\n  \ncontent:\n var(--header-subtitle, \"SUBVERTING COMMON PRACTICE\")\n;\n  \nfont-weight:\n \n700\n;\n  \nfont-size:\n \n1.2\nem\n;\n\n}\n\n \n\n@media\n (max-width: 707\npx\n) \n{\n\n    \n#header\n \nh1\n \na:\n:before {\n        font-size: \n1.6\nem\n;\n    \n}\n\n}\n \n\n#login-status\n,\n\n#login-status\n \na\n \n{\n\n    \ncolor:\n \n#333333\n;\n\n}\n\n \n\n#page-title\n \n{\n\n    \ndisplay:\n \nnone\n;\n\n}\n\n \n\n#footer\n, \n#footer\n \na\n \n{\n\n    \nbackground:\n \ntransparent\n;\n    \ncolor:\n \n#333333\n;\n\n}\n\n \n\n#search-top-box-input\n,\n\n#search-top-box-input\n:hover\n,\n\n#search-top-box-input\n:focus\n,\n\n#search-top-box-form\n \ninput\n[\ntype\n=\nsubmit\n]\n,\n\n#search-top-box-form\n \ninput\n[\ntype\n=\nsubmit\n]\n:hover\n,\n\n#search-top-box-form\n \ninput\n[\ntype\n=\nsubmit\n]\n:focus\n \n{\n\n    \nborder:\n \nnone\n;\n    \nbackground:\n \n#333333\n;\n    \nbox-shadow:\n \nnone\n;\n    \nborder-radius:\n \n0\npx\n;\n    \ncolor:\n \n#efefef\n;\n\n}\n\n \n\n#search-top-box\n \ninput.empty\n \n{\n\n    \ncolor:\n \n#999999\n;\n\n}\n\n \n\n#search-top-box\n \n{\n\n    \ntop:\n \n2.3\nrem!important\n;\n    \nright:\n \n8\npx\n;\n\n}\n\n \n\n#top-bar\n \n{\n \n   \ndisplay:\n flex\n;\n   \njustify-content:\n \ncenter\n;\n   \nright:\n \n0\n;\n   \ntop:\n \n7.9\nrem\n;\n\n}\n\n \n\n#top-bar\n, \n#top-bar\n \na\n \n{\n\n    \ncolor:\n \n#333333\n;\n\n}\n\n \n\nh1\n,\n\nh2\n,\n\nh3\n,\n\nh4\n,\n\nh5\n,\n\nh6\n \n{\n\n    \nfont-family:\n 'Montserrat', \nsans-serif\n;\n    \ncolor:\n \n#000\n;\n    \nletter-spacing:\n \n1\npx\n;\n\n}\n\n \n\nh1\n \n{\n\n    \nfont-size:\n \n2\nem\n;\n\n}\n\n \n\nh2\n \n{\n\n    \nfont-size:\n \n1.45\nem\n;\n\n}\n\n \n\ndiv#extra-div-1\n \n{\n\n    \nheight:\n \n160\npx\n;\n    \nwidth:\n \n100\n%\n;\n    \ntop:\n \n0\n;\n    \nposition:\n \nabsolute\n;\n    \nbackground:\n url('https://scp-wiki.wdfiles.com/local--files/theme%\n3\nAblankstyle/\n43\nHead.png')\n;\n    \nbackground-size:\n contain\n;\n    \nbackground-repeat:\n \nno-repeat\n;\n    \nbackground-position:\n \n50\n%\n \n50\n%\n;\n    \nz-index:\n -\n1\n;\n\n}\n\n \n\n@media\n (max-width: 707\npx\n) \n{\n\n    \ndiv#extra-div-1\n \n{\n\n        \ntop:\n \n15\npx\n;\n    \n}\n\n\n}\n\n \n\nbody\n \n{\n\n    \nbackground-image:\n linear-gradient(\n        to \nbottom\n,\n        \n#e0e0e0\n, \n#e0e0e0\n \n90\npx\n,\n        \n#e0e0e0\n \n90\npx\n, \n#ffffff\n \n200\npx\n,\n        \n#ffffff\n \n200\npx\n, \n#ffffff\n \n100\n%\n)\n;\n    \nbackground-repeat:\n \nno-repeat\n;\n\n}\n\n \n\n:root\n \n{\n\n  --\ntimeScale:\n \n1.5\n;\n  --\ntimeDelay:\n \n1.5\ns\n;\n  --\nposX:\n calc(\n50\n%\n - \n358\npx\n - \n13\nrem)\n;\n  --\nfnLinger:\n \n1\ns\n;\n\n}\n\n \n\n#page-content\n \nhr\n \n{\n\n    \nbackground-color:\n \n#000\n;\n\n}\n\n \n\n#page-content\n \ntr\n \nth\n \n{\n\n    \npadding:\n \n6\npx\n;\n    \nborder:\n \n#000\n \n1\npx\n \nsolid\n;\n\n}\n\n \n\n#page-content\n \ntr\n \ntd\n \n{\n\n    \npadding:\n \n12\npx\n;\n    \nborder:\n \n#000\n \n1\npx\n \nsolid\n;\n    \nline-height:\n \n1.4\n;\n\n}\n\n \n\n#page-content\n \n.sidebox\n \ntr\n \ntd\n, \n\n#page-content\n \n.sidebox\n \ntr\n \nth\n \n{\n\n    \npadding:\n \n0.35\nem\n;\n\n}\n\n \n\n#side-bar\n \n{\n\n    \nborder-right:\n \n1\npx\n \nsolid\n \n#333\n;\n    \nbackground:\n \n#DDD\n;\n\n}\n\n \n\n#side-bar\n \n.side-block\n \n{\n\n    \nborder:\n \n1\npx\n \nsolid\n \n#333\n;\n    \nborder-radius:\n \n0\n;\n    \nbox-shadow:\n \nnone\n;\n\n}\n\n \n\n#top-bar\n \ndiv.open-menu\n \na\n \n{\n\n    \nborder:\n \n1\npx\n \nsolid\n \n#333\n;\n    \nborder-radius:\n \n0\n;\n    \nbox-shadow:\n \nnone\n;\n\n}\n\n \n\n@media\n (max-width: 767\npx\n) \n{\n\n    \n#side-bar\n:\ntarget\n \n{\n\n        \nborder:\n \n1\npx\n \nblack\n;\n        \nbox-shadow:\n \nnone\n;\n    \n}\n\n\n}\n\n \n\n#side-bar\n \n.side-block\n \n{\n\n    \nborder:\n \n1\npx\n \nsolid\n \n#333\n;\n    \nborder-radius:\n \n0\n;\n    \nbox-shadow:\n \nnone\n;\n    \nbackground-color:\n \n#FDF6D7\n;\n\n}\n\n\n#side-bar\n \n.side-block.media\n \n{\n\n    \nbackground-color:\n#D7EFE7\n;\n\n}\n\n\n#side-bar\n \n.side-block.resources\n \n{\n\n    \nbackground-color:\n#F5D8E0\n;\n\n}\n\n \n\n#page-content\n \n.creditRate\n{\n\n    \nmargin:\n unset\n;\n    \nmargin-bottom:\n \n4\npx\n;\n\n}\n\n\n#page-content\n \n.rate-box-with-credit-button\n \n{\n\n    \nbackground-color:\n \n#ffffff\n;\n    \nborder:\n \nsolid\n \n1\npx\n \n#000\n;\n    \nbox-shadow:\n \nnone\n;\n    \nborder-radius:\n \n0\n;\n\n}\n\n \n\n#page-content\n \n.rate-box-with-credit-button\n \n.fa-info\n \n{\n\n    \nborder:\n \nnone\n;\n    \ncolor:\n \n#333333\n;\n\n}\n\n \n\n#page-content\n \n.rate-box-with-credit-button\n \n.fa-info\n:hover\n \n{\n\n    \nbackground:\n \n#333333\n;\n    \ncolor:\n \n#ffffff\n;\n\n}\n\n \n\n.rate-box-with-credit-button\n \n.cancel\n \n{\n\n    \nborder:\n \nsolid\n \n1\npx\n \n#ffffff\n;\n\n}\n\n \n/\n*\n ---- \nPAGE\n \nRATING\n ---- \n*\n/\n \n\n.page-rate-widget-box\n \n{\n\n    \nbox-shadow:\n \nnone\n;\n    \nborder:\n \nsolid\n \n1\npx\n \n#000\n;\n    \nmargin:\n unset\n;\n    \nmargin-bottom:\n \n4\npx\n;\n    \nborder-radius:\n \n0\n;\n\n}\n\n \n\ndiv.page-rate-widget-box\n \n.rate-points\n \n{\n\n    \nbackground-color:\n \n#ffffff\n;\n    \ncolor:\n \n#333333\n;\n    \nborder:\n \nnone\n;\n    \nborder-radius:\n \n0\n;\n\n}\n\n\n.page-rate-widget-box\n \n.rateup\n,\n\n.page-rate-widget-box\n \n.ratedown\n \n{\n\n    \nbackground-color:\n \n#ffffff\n;\n    \nborder-top:\n \nnone\n;\n    \nborder-bottom:\n \nnone\n;\n\n}\n\n \n\n.page-rate-widget-box\n \n.rateup\n \na\n,\n\n.page-rate-widget-box\n \n.ratedown\n \na\n \n{\n\n    \nbackground:\n \ntransparent\n;\n    \ncolor:\n \n#333333\n;\n\n}\n\n \n\n.page-rate-widget-box\n \n.rateup\n \na\n:hover\n,\n\n.page-rate-widget-box\n \n.ratedown\n \na\n:hover\n \n{\n\n    \nbackground:\n \n#333333\n;\n    \ncolor:\n \n#ffffff\n;\n\n}\n\n \n\n.page-rate-widget-box\n \n.cancel\n \n{\n\n    \nbackground:\n \ntransparent\n;\n    \nbackground-color:\n \n#ffffff\n;\n    \nborder:\n \nnone\n;\n    \nborder-radius:\n \n0\n;\n\n}\n\n \n\n.page-rate-widget-box\n \n.cancel\n \na\n \n{\n\n    \ncolor:\n \n#333333\n;\n\n}\n\n\n.page-rate-widget-box\n \n.cancel\n \na\n:hover\n \n{\n\n    \nbackground:\n \n#333333\n;\n    \ncolor:\n \n#ffffff\n;\n    \nborder-radius:\n \n0\n;\n\n}\n\n\n#page-content\n \n.rate-box-with-credit-button\n \n.page-rate-widget-box\n \n{\n \nborder:\n \nnone\n; \n}\n\n \n\n.anchor\n \n{\n\n    \nposition:\n sticky\n;\n    \nheight:\n0\n;\n    \ntop:\n \n0\n;\n\n}\n\n\n.sidebox\n \n{\n\n    \npadding:\n \n.14\nrem\n;\n    \nmargin-top:\n \n0\n;\n    \nmargin-bottom:\n \n8\npx\n;\n    \nwidth:\n calc((\n100\nvw - \n870\npx\n)/\n2\n)\n;\n    \nmax-height:\n calc(\n100\nvh - \n18\nrem)\n;\n    \nposition:\n \nabsolute\n;\n    \ntop:\n \n0\n;\n    \nleft:\n \n103.5\n%\n;\n    \nz-index:\n \n5\n;\n    \noverflow:\n \nauto\n;\n    \nbox-sizing:\n border-box\n;\n\n}\n\n\n@media\n (max-width: 1290\npx\n) \n{\n\n    \n.sidebox\n \n{\n\n        \ndisplay:\n \nnone\n;\n        \nvisibility:\n \nhidden\n;\n    \n}\n\n \n    \n#header\n \nh2:\n:before {\n        font-size: \n0.9\nem\n !important\n;\n    \n}\n\n}\n \n\n.scp-image-block\n \n{\n\n    \nbox-shadow:\n \nnone\n;\n\n}\n\n \n/\n*\n ---- \nYUI\n \nTAB\n \nBASE\n ---- \n*\n/\n\n.yui-navset\n \n.yui-nav\n \na\n,\n.yui-navset\n \n.yui-navset-top\n \n.yui-nav\n \na\n{\nbackground-color:\ninherit\n;\nbackground-image:\ninherit\n}\n.yui-navset\n \n.yui-nav\n \na\n:hover\n,\n.yui-navset\n \n.yui-nav\n \na\n:focus\n{\nbackground:\ninherit\n;\ntext-decoration:\ninherit\n}\n.yui-navset\n \n.yui-nav\n \n.selected\n \na\n,\n.yui-navset\n \n.yui-nav\n \n.selected\n \na\n:focus\n,\n.yui-navset\n \n.yui-nav\n \n.selected\n \na\n:hover\n{\ncolor:\ninherit\n;\nbackground:\ninherit\n}\n.yui-navset\n \n.yui-nav\n,\n.yui-navset\n \n.yui-navset-top\n \n.yui-nav\n{\nborder-color:\ninherit\n}\n.yui-navset\n \nli\n{\nline-height:\ninherit\n}\n\n \n/\n*\n ---- \nYUI\n \nTAB\n \nCUSTOMIZATION\n ----\n*\n/\n \n \n.yui-navset\n \n.yui-nav\n,\n \n.yui-navset\n \n.yui-navset-top\n \n.yui-nav\n{\n\n     \ndisplay:\n flex\n;\n     \nflex-wrap:\n wrap\n;\n     \nwidth:\n calc(\n100\n%\n - \n.125\nrem)\n;\n     \nmargin:\n \n0\n \nauto\n;\n     \nborder-color:\n \n#333333\n;\n     \nbox-shadow:\n \nnone\n;\n\n}\n\n \n.yui-navset\n \n.yui-nav\n \na\n, /\n*\n ---- \nLink\n \nModifier\n ---- \n*\n/\n \n.yui-navset\n \n.yui-navset-top\n \n.yui-nav\n \na\n{\n\n     \ncolor:\n \n#333333\n;\n    /\n*\n ---- \nTab\n \nBackground\n \nColour\n | [\nUNSELECTED\n] ---- \n*\n/\n     \nbackground-color:\n \n#efefef\n;\n     \nborder:\n unset\n;\n     \nbox-shadow:\n \nnone\n;\n     \nbox-shadow:\n \nnone\n;\n\n}\n\n \n.yui-navset\n \n.yui-nav\n \na\n:hover\n,\n \n.yui-navset\n \n.yui-nav\n \na\n:focus\n{\n\n     \ncolor:\n \n#ffffff\n;\n    /\n*\n ---- \nTab\n \nBackground\n \nColour\n | [\nHOVER\n] ---- \n*\n/\n     \nbackground-color:\n \n#333333\n;\n\n}\n\n \n.yui-navset\n \n.yui-nav\n \nli\n, /\n*\n ---- \nListitem\n \nModifier\n ---- \n*\n/\n \n.yui-navset\n \n.yui-navset-top\n \n.yui-nav\n \nli\n{\n\n     \nposition:\n \nrelative\n;\n     \ndisplay:\n flex\n;\n     \nflex-grow:\n \n2\n;\n     \nmax-width:\n \n100\n%\n;\n     \nmargin:\n \n0\n;\n     \npadding:\n \n0\n;\n     \ncolor:\n \n#ffffff\n;\n     \nbackground-color:\n \n#ffffff\n;\n     \nborder-color:\n \ntransparent\n;\n     \nbox-shadow:\n \nnone\n;\n\n}\n\n \n.yui-navset\n \n.yui-nav\n \nli\n \na\n,\n \n.yui-navset-top\n \n.yui-nav\n \nli\n \na\n,\n \n.yui-navset-bottom\n \n.yui-nav\n \nli\n \na\n{\n\n     \ndisplay:\n flex\n;\n     \nalign-items:\n \ncenter\n;\n     \njustify-content:\n \ncenter\n;\n     \nwidth:\n \n100\n%\n;\n\n}\n\n \n.yui-navset\n \n.yui-nav\n \nli\n \nem\n{\n\n     \nborder:\n unset\n;\n\n}\n\n \n.yui-navset\n \n.yui-nav\n \na\n \nem\n,\n \n.yui-navset\n \n.yui-navset-top\n \n.yui-nav\n \na\n \nem\n{\n\n     \npadding:\n \n.35\nem\n \n.75\nem\n;\n \n     \ntext-overflow:\n ellipsis\n;\n     \noverflow:\n \nhidden\n;\n     \nwhite-space:\n \nnowrap\n;\n\n}\n\n \n.yui-navset\n \n.yui-nav\n \n.selected\n, /\n*\n ---- \nSelection\n \nModifier\n ---- \n*\n/\n \n.yui-navset\n \n.yui-navset-top\n \n.yui-nav\n \n.selected\n{\n\n     \nflex-grow:\n \n2\n;\n     \nmargin:\n \n0\n;\n     \npadding:\n \n0\n;\n    /\n*\n ---- \nTab\n \nBackground\n \nColour\n | [\nSELECTED\n] ---- \n*\n/\n     \nbackground-color:\n \n#333333\n;\n\n}\n\n \n.yui-navset\n \n.yui-nav\n \n.selected\n \na\n,\n \n.yui-navset\n \n.yui-nav\n \n.selected\n \na\n \nem\n{\n\n     \nborder:\n \nnone\n;\n\n}\n\n \n.yui-navset\n \n.yui-nav\n \n.selected\n \na\n{\n\n     \nwidth:\n \n100\n%\n;\n     \ncolor:\n \n#ffffff\n;\n\n}\n\n \n.yui-navset\n \n.yui-nav\n \n.selected\n \na\n:focus\n,\n \n.yui-navset\n \n.yui-nav\n \n.selected\n \na\n:active\n{\n\n     \ncolor:\n \n#ffffff\n;\n     \nbackground-color:\n \n#333333\n;\n\n}\n\n \n.yui-navset\n \n.yui-content\n \n{\n\n    \nbackground-color:\n \n#ffffff\n;\n    \nbox-shadow:\n \nnone\n;\n\n}\n\n \n.yui-navset\n \n.yui-content\n,\n \n.yui-navset\n \n.yui-navset-top\n \n.yui-content\n{\n\n    \npadding:\n \n.5\nem\n;\n    \nborder:\n \n1\npx\n \nsolid\n \n#333\n;\n    \nbox-sizing:\n border-box\n;\n\n}\n\n \n/\n*\n---- \nSCROLLBAR\n ----\n*\n/\n \n::-\nwebkit-scrollbar\n \n{\n\n    \nwidth:\n \n10\npx\n;\n\n}\n\n \n::-\nwebkit-scrollbar-track\n \n{\n\n    \nbackground:\n \n#FFF\n;\n    \nborder-left:\n \n1\npx\n \nsolid\n \n#333\n;\n\n}\n\n \n::-\nwebkit-scrollbar-thumb\n \n{\n\n     \nbackground:\n \n#CCC\n;\n     \nborder:\n \n#333\n \n1\npx\n \nsolid\n;\n\n}\n\n \n::-\nwebkit-scrollbar-thumb\n:hover\n \n{\n\n     \nbackground:\n \n#EEE\n;\n\n}\n\n \n/\n*\n---- \nCENTER\n \nIMAGES\n \nON\n \nMOBILE\n \ncourtesy\n \nof\n \nEstrellaYoshte\n \nand\n \nPeppersGhost\n ----\n*\n/\n \n\n.imagediv\n \n{\n\n    \nfloat:\n \nright\n;\n    \nmargin:\n \n15\npx\n\n\n}\n\n \n\n@media\n (max-width: 540\npx\n) \n{\n\n  \n.imagediv\n \n{\n\n    \nfloat:\n \nnone\n;\n    \ntext-align:\ncenter\n;\n    \nmargin:\n \nauto\n;\n  \n}\n\n\n}\n\n \n\n@media\n \nonly\n \nscreen\n \nand\n (max-width: 600\npx\n) \n{\n\n    \n.scp-image-block.block-right\n{\n\n        \nfloat:\n \nnone\n;\n        \nmargin:\n \n10\npx\n \nauto\n;\n    \n}\n\n\n}\n\n \n/\n*\n---- \nACS-COLORED\n \nTABLE\n \nDIVS\n ----\n*\n/\n \n\n#page-content\n \n.table1\n \ntr\n \nth\n,\n\n#page-content\n \n.table1\n \n.scp-image-block\n \n.scp-image-caption\n \n{\n\n    \nbackground-color:\n \n#D7EFE7\n;\n\n}\n\n \n\n#page-content\n \n.table2\n \ntr\n \nth\n,\n\n#page-content\n \n.table2\n \n.scp-image-block\n \n.scp-image-caption\n \n{\n\n    \nbackground-color:\n \n#D8ECF4\n;\n\n}\n\n \n\n#page-content\n \n.table3\n \ntr\n \nth\n,\n\n#page-content\n \n.table3\n \n.scp-image-block\n \n.scp-image-caption\n \n{\n\n    \nbackground-color:\n \n#FDF6D7\n;\n\n}\n\n \n\n#page-content\n \n.table4\n \ntr\n \nth\n,\n\n#page-content\n \n.table4\n \n.scp-image-block\n \n.scp-image-caption\n \n{\n\n    \nbackground-color:\n \n#FFDABF\n;\n\n}\n\n \n\n#page-content\n \n.table5\n \ntr\n \nth\n,\n\n#page-content\n \n.table5\n \n.scp-image-block\n \n.scp-image-caption\n \n{\n\n    \nbackground-color:\n \n#F5D8E0\n;\n\n}\n\n \n\n#page-content\n \n.table6\n \ntr\n \nth\n,\n\n#page-content\n \n.table6\n \n.scp-image-block\n \n.scp-image-caption\n \n{\n\n    \nbackground-color:\n rgba(\n146\n, \n0\n, \n255\n, \n0.2\n)\n;\n\n}\n\n \n\n.tableb\n \n.wiki-content-table\n \n{\n\n    \nborder-collapse:\n \nseparate\n;\n    \nborder-spacing:\n \n2\npx\n;\n\n}\n\n \n\n.tableb\n \n.scp-image-block\n \n{\n\n    \nborder:\n \nnone\n;\n\n}\n\n \n\n.tableb\n \n.scp-image-block\n \nimg\n \n{\n\n    \nborder:\n \n#000\n \n1\npx\n \nsolid\n;\n    \nbox-sizing:\n border-box\n;\n\n}\n\n \n\n.tableb\n \n.scp-image-block\n \n.scp-image-caption\n \n{\n\n    \nmargin-top:\n \n2\npx\n;\n    \nborder:\n \n#000\n \n1\npx\n \nsolid\n;\n    \nbox-sizing:\n border-box\n;\n\n}\n\n \n\n.top-left-box\n > \n.item\n \n{\n\n  \ndisplay:\n \nnone\n;\n\n}\n\n \n/\n*\n ---- \nWORDS\n \nNO\n \nLONGER\n \nBROKEN\n, \nTHE\n \nCROQUEMBOUCHE\n \nHAS\n \nSPOKEN\n ---- \n*\n/\n\nspan\n, \na\n \n{\n \nword-break:\n \nnormal\n !important \n}\n\n \n\n.avatar-hover\n \n{\n \ndisplay:\n \nnone\n !important\n; \n}\n\n \n\n#breadcrumbs\n, \n.pseudocrumbs\n \n{\n\n    \ntext-align:\n \ncenter\n;\n    \npadding-top:\n \n10\npx\n;\n\n}\n\n \n\n#main-content\n \n.page-tags\n \nspan\n \n{\n\n    \nmax-width:\n \n100\n%\n;\n\n}\n\n \n/\n*\n -- \nFANCY\n \nTHINGS\n \nfrom\n \nWoedenaz\n'\ns\n \nDustjacket\n \nTheme\n -- \n*\n/\n \n\n.fancyhr\n \nhr\n \n{\n\n    \nborder-top:\n \n2\nvw \nsolid\n \ntransparent\n;\n    \nbackground-color:\n rgba(var(--bright-accent), \n0\n)\n;\n    \nheight:\n \n0\n;\n    \nbox-sizing:\n border-box\n;\n    \nborder-image-source:\n url('https://scp-wiki.wdfiles.com/local--files/theme%\n3\nAflopstyle-dark/wl_hr.png')\n;\n    \nborder-image-repeat:\n round round\n;\n    \nbackground:\n \nnone\n;\n    \nborder-image-slice:\n \n80\n \n500\n \n80\n \n500\n fill\n;\n    \nborder-image-width:\n \n10\nem\n \n80\nem\n \n10\nem\n \n80\nem\n;\n\n}\n\n \n\n.fancyborder\n \n{\n\n    \nbox-sizing:\n border-box\n;\n    \nborder:\n \n2\nvw \nsolid\n rgba(\n0\n,\n0\n,\n0\n,\n0.5\n)\n;\n    \nborder-image:\n url('https://scp-wiki.wdfiles.com/local--files/theme%\n3\nAflopstyle-dark/wl_border.png') \n600\n round\n;\n    \nborder-image-width:\n \n6\n;\n    \npadding:\n \n2\nvw\n;\n\n}\n\n\n\n\n\n\n\n\n\n\n\n\n\n\n\n\n \n\n\nrating:\u00a0\n+102\n+\n\u2013\nx\n\n\n\n\n\n\nThe hallway affected by SCP-6911.\n\n\n\n\n\n\nItem #:\n SCP-6911\n\n\nObject Class:\n Euclid\n\n\nSpecial Containment Procedures:\n Dr. Everwood's office has been decommissioned. No personnel are permitted to attempt to enter the room outside of SCP-6911 testing periods.\n\n\nDescription:\n SCP-6911 is a spatial anomaly occurring on hall E, floor 2B of \nSite-55\n's personnel offices. The anomaly is activated when a human subject enters the hallway with the intent of entering Dr. Everwood's office. When active, SCP-6911 will shrink the hallway, thus rendering it impossible to proceed beyond a certain point. If other individuals are present in the hallway when SCP-6911 is triggered, they will be pushed beyond the threshold of the shrinking effect.\n\n\nDr. Everwood is the only individual capable of bypassing SCP-6911 entirely.\n\n\nAddendum 6911.A- Interview:\n Dr. Everwood was interviewed by \nNhung Ngo\n, a psychiatrist consultant from the Spatial Anomalies Department, shortly after the discovery of SCP-6911 to ascertain any involvement or probable origins of SCP-6911.\n\n\n\n\n<BEGIN LOG>\n\n\nNgo:\n Hello, Jay. I know you're busy, but as I'm sure you're aware-\n\n\nEverwood:\n Yeah, I know, I know. My office is an SCP now. Great.\n\n\nNgo:\n Well, not your office per se, but the hallway leading to it.\n\n\nEverwood:\n Either way, the whole thing has me quite cheesed.\n\n\nNgo:\n I'll try to be brief then. As I was saying, you're the only person who can successfully bypass SCP-6911.\n\n\nEverwood:\n Trust me, if I knew why or how this happened, you'd be the first to know. And much to my surprise, I haven't just become magic despite my best efforts to the contrary.\n\n\nNgo:\n You're saying you've been trying to learn thaumaturgy?\n\n\nEverwood:\n That was a joke, Nhung.\n\n\nNgo:\n Oh. Sorry. They don't get many jokesters over at Spatial Anomalies.\n\n\nEverwood:\n Figures they'd all be squares.\n\n\nNgo:\n \u2026\n\n\nEverwood:\n That was a joke as well. Come on, cut me some slack. I've gotta cope with my office being fucked somehow.\n\n\nNgo:\n Fair enough. So listen Jay, I just have a couple of questions about what's happened in your office the last few days, alright?\n\n\nEverwood:\n Sure.\n\n\nNgo:\n Alright. So for starters, have any anomalous objects entered your office?\n\n\nEverwood:\n Yeah. More than I could count. The Junior Researchers come to my office carrying just about anything they get their mitts on. I get it, they're mostly clueless, but just because the pen has the MC&D logo on it doesn't mean it's anomalous. Give me a break.\n\n\nNgo:\n Any idea of their SCP item designation?\n\n\nEverwood:\n Nope. Do you have any idea how many items come across my desk every day? Every time someone finds something from an external group of interest, it's dropped in my lap. A jinn lamp from ORIA? It's been in my office. Tapioca pearls from Marshall, Carter, and Dark? You bet they've been in my office. An anti-theology explosive from SAPPHIRE? Yup, in my office. I could go on.\n\n\nNgo:\n Point taken.\n\n\nEverwood:\n Actually, I will go on. Consultations are draining my very soul. The moment someone suspects a GoI even so much as farted in the direction of their object, they come to me. Just the other day I had a fucking \ndowsing rod\n, you know those useless sticks that supposedly detect water? The fool thought it detected anomalies. And just because the people they confiscated it from were Parawatch users, they brought that up to my office.\n\n\nNgo:\n I, err\u2026\n\n\nEverwood:\n Fucking Parawatch. Those people aren't even on the same side of the veil we are. I had to explain to him that no, they hadn't just magically gained powers and that he had brought a glorified stick into my office. Jeez, Louise.\n\n\nNgo:\n I'm sorry. It sounds like you're very stressed out.\n\n\nEverwood:\n Sorry. It's been a rough few\u2026 weeks? Months? Years? Anyway, next question, please.\n\n\nNgo:\n You already said you aren't practicing thaumaturgy. So that leaves me out of questions, actually.\n\n\nEverwood:\n You know, I don't know if this is important at all, but I think I should say it. I just kind of wished that I could have some peace and quiet. And I did have it! For a few hours, anyway. Later I come to find that the hallway my office is in was quarantined and apparently this happened. I feel stupid even saying this out loud, but it's the truth.\n\n\nNgo:\n I see.\n\n\nEverwood:\n Sometimes weird things just happen though, don't they?\n\n\nNgo:\n I suppose they do. But you know what? I have an idea that may solve this little problem of yours.\n\n\nEverwood:\n Do tell.\n\n\n<END LOG>\n\n\n\n\nAddendum 6911.02:\n Following the interview, Dr. Ngo suggested Dr. Everwood take on a research assistant. Researcher Rex Alces was selected by Dr. Everwood, who now oversees a portion of their previously assigned work including consultations and item assessment.\n\n\nSCP-6911 has not manifested since this change. Reclassification to Neutralized is currently pending.\n\n\n \n\n\n \n\n\n \n\n\n\n\n\n\nMore\u00a0From\u00a0This\u00a0Author\n\n\n\n\nMore\u00a0From\u00a0This\u00a0Author\n\n\n\n\n\n\n\n\n \n\n\nUncle Nicolini's Works\n\n\n\n\n\n\n\n\n\n\nSCPs\n\n\n \n\n\nSCP-1841\n \n\u2022\n\n\n\n\n\n\nSCP-3867\n \n\u2022\n\n\n\n\n\n\nSCP-4056\n \n\u2022\n\n\n\n\n\n\nSCP-726-EX\n \n\u2022\n\n\n\n\n\n\nSCP-7573\n \n\u2022\n\n\n\n\n\n\nSCP-371-J\n \n\u2022\n\n\n\n\n\n\nMDI-6726\n \n\u2022\n\n\n\n\n\n\nSCP-ES-101-J\n \n\u2022\n\n\n\n\n\n\nSCP-3874\n \n\u2022\n\n\n\n\n\n\nSCP-3085\n \n\u2022\n\n\n\n\n\n\nSCP-7726\n \n\u2022\n\n\n\n\n\n\nSCP-7221\n \n\u2022\n\n\n\n\n\n\nSCP-4026\n \n\u2022\n\n\n\n\n\n\nSCP-3756\n \n\u2022\n\n\n\n\n\n\nSCP-6512\n \n\u2022\n\n\n\n\n\n\n\n\n\n\nTales/GoI Formats\n\n\n \n\n\nBefore the Storm\n \n\u2022\n\n\n\n\n\n\nShape Shift With Me\n \n\u2022\n\n\n\n\n\n\nManhattan Dimensional Collapse; GOC Intervention Imminent?\n \n\u2022\n\n\n\n\n\n\nSPC-7000\n \n\u2022\n\n\n\n\n\n\nThe Hermit, Death, and The Devil\n \n\u2022\n\n\n\n\n\n\nTwo Minutes To Midnight\n \n\u2022\n\n\n\n\n\n\n\u9b42-S-2049 \"Anima Back-Ups\"\n \n\u2022\n\n\n\n\n\n\nMoon Champion's Cinco de Mayo Extravaganza\n \n\u2022\n\n\n\n\n\n\nSC-99/734/01/506\n \n\u2022\n\n\n\n\n\n\nI Don't Get It, But I'll Figure It Out.\n \n\u2022\n\n\n\n\n\n\nSquare your shoulders, lift your pack, and leave your friends and go.\n \n\u2022\n\n\n\n\n\n\nGRANT REQUEST FOR THE RE-CREATION OF AN ADVANCED POSTMORTEM NEURAL PRESERVATION SYSTEM\n \n\u2022\n\n\n\n\n\n\nSPC-446\n \n\u2022\n\n\n\n\n\n\nJust Another Day\n \n\u2022\n\n\n\n\n\n\nWilson's Wildlife Solutions Orientation\n \n\u2022\n\n\n\n\n\n\n\n\n\n\nOther\n\n\n \n\n\nuncle nicolini author page\n \n\u2022\n\n\n\n\n\n\nSciptember 2022 Art Highlights\n \n\u2022\n\n\n\n\n\n\nOde To The Unknown Author\n \n\u2022\n\n\n\n\n\n\n\n\n\n\n\n\n\n\n\n\n\n\n\n\n\n\n\u00ab \nSCP-6910\n | SCP-6911 | \nSCP-6912\n \u00bb\n\n\n\n\n\n\n\n\n\n\n\u2021\u00a0Licensing\u00a0/\u00a0Citation\n\n\n\n\n\u2021\u00a0Hide\u00a0Licensing\u00a0/\u00a0Citation\n\n\n\n\nCite this page as:\n\n\n \n\n\n\n\n\"\nSCP-6911\n\" by Uncle Nicolini, from the \nSCP Wiki\n. Source: \nhttps://scpwiki.com/scp-6911\n. Licensed under \nCC-BY-SA\n.\n\n\n\n\n\n\n\n\nFor information on how to use this component, see the \nLicense Box component\n. To read about licensing policy, see the \nLicensing Guide\n.\n\n\n\n\n\n\nFilename:\n hallway.jpg\n\n\nName:\n Endless Corridor\n\n\nAuthor:\n elPadawan\n\n\nLicense:\n CC BY SA 2.01.0\n\n\nSource Link:\n \nhttps://www.flickr.com/photos/elpadawan/5822542422",
    "addendums": [
        "Addendum 6911.A- Interview: Dr. Everwood was interviewed by Nhung Ngo , a psychiatrist consultant from the Spatial Anomalies Department, shortly after the discovery of SCP-6911 to ascertain any involvement or probable origins of SCP-6911.",
        "Addendum 6911.02: Following the interview, Dr. Ngo suggested Dr. Everwood take on a research assistant. Researcher Rex Alces was selected by Dr. Everwood, who now oversees a portion of their previously assigned work including consultations and item assessment.\nSCP-6911 has not manifested since this change. Reclassification to Neutralized is currently pending."
    ],
    "documents": [],
    "notes": [
        "\" SCP-6911 \" by Uncle Nicolini, from the SCP Wiki . Source: https://scpwiki.com/scp-6911 . Licensed under CC-BY-SA .",
        "Filename: hallway.jpg Name: Endless Corridor Author: elPadawan License: CC BY SA 2.01.0 Source Link: https://www.flickr.com/photos/elpadawan/5822542422"
    ],
    "item": "SCP-6911",
    "object_class": "Euclid",
    "containment_procedures": "Dr. Everwood's office has been decommissioned. No personnel are permitted to attempt to enter the room outside of SCP-6911 testing periods.",
    "description": "SCP-6911 is a spatial anomaly occurring on hall E, floor 2B of Site-55's personnel offices. The anomaly is activated when a human subject enters the hallway with the intent of entering Dr. Everwood's office. When active, SCP-6911 will shrink the hallway, thus rendering it impossible to proceed beyond a certain point. If other individuals are present in the hallway when SCP-6911 is triggered, they will be pushed beyond the threshold of the shrinking effect.",
    "title": "SCP-6911"
}