{
    "url": "https://scp-wiki.wikidot.com/scp-6982",
    "all_text": "SCP-6982\n\n\n\n\n\n\nBy:\n \nNebulousStar\n\n\n\n\n\n\nPublished on \n07 Oct 2021 20:35\n\n\n\n\n\n\n\n\n\n\n\n\n\n\n\n\nrating:\u00a0\n+87\n+\n\u2013\nx\n\n\n\n\nState your name for the record.\n\n\n\n\n \n\n\n\n\nA birthday party. Fifth, maybe? Seventh?\n\n\nA kid sat alone. It was her birthday, yet no one cared. She listened to the laughter around her.\n\n\nShe knew they were just here for the cake.\n\n\n\n\n\n\n \n\n\n\n\n\n\nJayden Carver.\n\n\n\n\n\n\n\n\n \n\n\n\n\nHow did you find out about the Foundation?\n\n\n\n\n \n\n\n\n\n\n\nI just\u2026 know.\n\n\n\n\n\n\n\n\n \n\n\n\n\nThe ball flew by. She turned her head, but she stayed where she was. She never really liked sports.\n\n\nThey screamed at her to go. It didn't matter.\n\n\n\n\n\n\n \n\n\n\n\nYou just know?\n\n\n\n\n \n\n\n\n\n\n\nI just know. What more is there to say?\n\n\n\n\n\n\n\n\n \n\n\n\n\nAlright, moving on. What made you come here?\n\n\n\n\n \n\n\n\n\n\"Nora?\"\n\n\nThe kids around her snickered. She rubbed her eyes. \"Huh?\"\n\n\n\n\n\n\n \n\n\n\n\n\n\nI think\u2026 I was supposed to.\n\n\n\n\n\n\n\n\n \n\n\n\n\nElaborate.\n\n\n\n\n \n\n\n\n\n\n\nIt has to do with the knowledge. I\u2026\n\n\n\n\n\n\n\n\n \n\n\n\n\nA loud bang.\n\n\nShe had dropped her textbook.\n\n\n\n\n\n\n \n\n\n\n\nYou what?\n\n\n\n\n \n\n\n\n\nScreaming. Disappointment.\n\n\nBad grades.\n\n\nA promise.\n\n\n\n\n\n\n \n\n\n\n\n\n\nI don't know.\n\n\n\n\n\n\n\n\n \n\n\n\n\nCan't go.\n\n\nFrustration.\n\n\n\n\n\n\n \n\n\n\n\n\n\nI don't\u2026 know what I was saying.\n\n\n\n\n\n\n\n\n \n\n\n\n\nLonely.\n\n\n\n\n\n\n \n\n\n\n\nA friend.\n\n\nSomeone who wouldn't leave.\n\n\n\n\n\n\n \n\n\n\n\nOkay, what's going on?\n\n\n\n\n \n\n\n\n\nA job offer.\n\n\nStuck.\n\n\n\n\n\n\n \n\n\n\n\n\n\nYour, uh, your memories\u2026\n\n\n\n\n\n\n\n\n \n\n\n\n\nA secret.\n\n\nA horrible secret.\n\n\n\n\n\n\n \n\n\n\n\nMy memories?\n\n\n\n\n \n\n\n\n\nA ritual.\n\n\nA sickness.\n\n\nA gun.\n\n\n\n\n\n\n \n\n\n\n\n\n\nIt's not right, though. I've been seeing\u2026\n\n\n\n\n\n\n\n\n \n\n\n\n\nA gun.\n\n\n\n\n\n\n \n\n\n\n\n \n\n\n\n\nYou mentioned my memories yesterday. What'd you mean?\n\n\n\n\n \n\n\n\n\n\n\nI don't\u2026 I don't remember what I said.\n\n\n\n\n\n\n\n\n \n\n\n\n\nCheering. Congratulations.\n\n\nShe could barely hear them over the static. They were happy for her, but\u2026\n\n\nIs this a branch?\n\n\n\n\n\n\n \n\n\n\n\nAfter I asked what was going on?\n\n\n\n\n \n\n\n\n\nScreaming.\n\n\nAn argument right as she tried to speak. She sat at the table, but it didn't mean anything.\n\n\n\n\n\n\n \n\n\n\n\n\n\nOh.\n\n\n\n\n\n\n\n\n \n\n\n\n\nShe opened her mouth, but no words came out.\n\n\nA secret left forever untold.\n\n\n\n\n\n\n \n\n\n\n\nAre you always this\u2026 spacey?\n\n\n\n\n \n\n\n\n\n\n\nNot before. My condition's been getting worse.\n\n\n\n\n\n\n\n\n \n\n\n\n\nYour condition?\n\n\n\n\n \n\n\n\n\n\n\nI see memories. Not voluntarily.\n\n\n\n\n\n\n\n\n \n\n\n\n\nThe animal froze, eyes wide.\n\n\nShe slammed on the brakes.\n\n\nGlass flying through the air.\n\n\nA sharp pain.\n\n\nIt was too late to make amends.\n\n\n\n\n\n\n \n\n\n\n\nShit. How much did you see?\n\n\n\n\n \n\n\n\n\n\n\nYou won't like the answer no matter what I say.\n\n\n\n\n\n\n\n\n \n\n\n\n\nJust- let's keep this between us.\n\n\n\n\n \n\n\n\n\n \n\n\n\n\nHow well do you remember the memories you see?\n\n\n\n\n \n\n\n\n\n\n\nDepends. Some really stick with me, but others\u2026 I forget.\n\n\n\n\n\n\n\n\n \n\n\n\n\nAlright, uh, do you know anything about this?\n\n\n\n\n \n\n\n\n\nItem #:\n SCP-6982\n\n\nObject Class:\n Uncontained\n\n\nSpecial Containment Procedures:\n N/A\n\n\nDescription:\n SCP-6982 is a silver bowl. Human subjects observing SCP-6982 from above will perceive a series of images reflected inside of it.\n\n\nImages are as follows:\n\n\n\n\nA bottle of beer.\n\n\nA black car.\n\n\nA small child, approximated to be 4-6 years of age.\n\n\nA forest.\n\n\nA shovel.\n\n\n\n\n\n\n\n\n \n\n\n\n\nThis is\u2026\n\n\n\n\n\n\n \n\n\n\n\n\n\nYour, uh\u2026 I don't\u2026 think so.\n\n\n\n\n\n\n\n\n \n\n\n\n\nFair enough.\n\n\n\n\n \n\n\n\n\nMore time.\n\n\nAs she disappeared under the surface, she wished for more time.\n\n\n\n\n\n\n \n\n\n\n\n\n\nLook, I've seen your timelines.\n\n\n\n\n\n\n\n\n \n\n\n\n\nWhat?\n\n\n\n\n \n\n\n\n\n\n\nI've seen your futures, and you never tell anyone. You always die wishing you could've said something.\n\n\n\n\n\n\n\n\n \n\n\n\n\nSaid something\u2026\n\n\n\n\n \n\n\n\n\nShe grabbed her shovel.\n\n\nIt was time to dig up the past.\n\n\n\n\n\n\n \n\n\n\n\n\n\n\u00ab \nSCP-6981\n | SCP-6982 | \nSCP-6983\n \u00bb\n\n\n\n\n\n\n\n\n\n\n\u2021\u00a0Licensing\u00a0/\u00a0Citation\n\n\n\n\n\u2021\u00a0Hide\u00a0Licensing\u00a0/\u00a0Citation\n\n\n\n\nCite this page as:\n\n\n \n\n\n\n\n\"\nSCP-6982\n\" by NebulousStar, from the \nSCP Wiki\n. Source: \nhttps://scpwiki.com/scp-6982\n. Licensed under \nCC-BY-SA\n.\n\n\n\n\n\n\n\n\nFor information on how to use this component, see the \nLicense Box component\n. To read about licensing policy, see the \nLicensing Guide\n.",
    "addendums": [],
    "documents": [],
    "notes": [
        "State your name for the record.",
        "Jayden Carver.",
        "How did you find out about the Foundation?",
        "I just\u2026 know.",
        "You just know?",
        "I just know. What more is there to say?",
        "Alright, moving on. What made you come here?",
        "I think\u2026 I was supposed to.",
        "Elaborate.",
        "It has to do with the knowledge. I\u2026",
        "You what?",
        "I don't know.",
        "I don't\u2026 know what I was saying.",
        "Okay, what's going on?",
        "Your, uh, your memories\u2026",
        "My memories?",
        "It's not right, though. I've been seeing\u2026",
        "You mentioned my memories yesterday. What'd you mean?",
        "I don't\u2026 I don't remember what I said.",
        "After I asked what was going on?",
        "Oh.",
        "Are you always this\u2026 spacey?",
        "Not before. My condition's been getting worse.",
        "Your condition?",
        "I see memories. Not voluntarily.",
        "Shit. How much did you see?",
        "You won't like the answer no matter what I say.",
        "Just- let's keep this between us.",
        "How well do you remember the memories you see?",
        "Depends. Some really stick with me, but others\u2026 I forget.",
        "Alright, uh, do you know anything about this?",
        "Your, uh\u2026 I don't\u2026 think so.",
        "Fair enough.",
        "Look, I've seen your timelines.",
        "What?",
        "I've seen your futures, and you never tell anyone. You always die wishing you could've said something.",
        "Said something\u2026",
        "\" SCP-6982 \" by NebulousStar, from the SCP Wiki . Source: https://scpwiki.com/scp-6982 . Licensed under CC-BY-SA ."
    ],
    "item": "SCP-6982",
    "object_class": "Uncontained",
    "containment_procedures": "N/A",
    "description": "SCP-6982 is a silver bowl. Human subjects observing SCP-6982 from above will perceive a series of images reflected inside of it.",
    "title": "SCP-6982"
}