{
    "url": "https://scp-wiki.wikidot.com/scp-7684",
    "all_text": "rating:\u00a0\n+85\n+\n\u2013\nx\n\n\nItem #:\n SCP-7684\n\n\nObject Class:\n [OP-REQ INSUFFICIENT]\n\n\nSpecial Containment Procedures:\n [OP-REQ INSUFFICIENT]\n\n\nDescription:\n [OP-REQ INSUFFICIENT]\n\n\n\n\nDisplaying your associated support tickets\u2026\n\n\n\n\nTicket:\n #58KG4VO\n\n\nDate Filed:\n 10 NOV 2058\n\n\nImportance:\n Low\n\n\nSubject:\n SCP-7684 Display Error\n\n\nContent:\n\n\n\n\nWhile reviewing AIC-generated analyses, a redirect to the main SCP-7684 file threw up some errors (not redactions). Can somebody clear this up? Not urgent from my perspective, but it might be for people on the containment team. I'd appreciate a heads up when resolved so I can finish my review.\n\n\n\n\nResponse:\n\n\n\n\nThe SCP-7684 page is functioning as intended, but your operational requirement is insufficient to view it. Please consult your security representative.\n\n\n\n\nTicket Status:\n CLOSED\n\n\n\n\n\n\nTicket:\n #O5981A2\n\n\nDate Filed:\n 15 NOV 2058\n\n\nImportance:\n Medium\n\n\nSubject:\n SCP-7684 Page Not Pulling from PAGEANT\n\n\nContent:\n\n\n\n\nThe main SCP-7684 file continues displaying 'OP-REQ INSUFFICIENT' when viewed from any terminal. I consulted my DSEC, and she claims I am good to see scrubbed summaries of everything mainline. Can you confirm that accesses are being validated in PAGEANT? Others on my team had the same issue when double checking.\n\n\n\n\nResponse:\n\n\n\n\nPAGEANT is not certified for processing SCP-7684 accesses. Please consult your security representative to identify proper channels.\n\n\n\n\nTicket Status:\n CLOSED\n\n\n\n\n\n\nTicket:\n #9UU351K\n\n\nDate Filed:\n 03 DEC 2058\n\n\nImportance:\n Medium\n\n\nSubject:\n SCP-7684 Page Not Pulling from PAGEANT - V2\n\n\nContent:\n\n\n\n\nRefer to ticket #O5981A2 for context. My security representative cannot identify the correct system for validating SCP-7684 access. Can you direct me to the proper system/point of contact/etc.? This is getting a little silly even for this place.\n\n\n\n\nResponse:\n\n\n\n\nThis tool is not certified to handle that information. Please consult your security representative.\n\n\n\n\nTicket Status:\n CLOSED\n\n\n\n\n\n\nTicket:\n #5193T3N\n\n\nDate Filed:\n 04 DEC 2058\n\n\nImportance:\n High\n\n\nSubject:\n SCP-7684 Page Not Pulling from PAGEANT - V3!\n\n\nContent:\n\n\n\n\nRe: #9UU351K. Not to start a pissing contest, but this is pursuant to a direct tasking from the Deputy Assistant Director for Research and Development (NA). If assistance has to happen at a higher level, someone in your office needs to contact me at \nlanretni.noitadnuof.golc|22koorb.t#lanretni.noitadnuof.golc|22koorb.t\n.\n\n\n\n\nResponse:\n\n\n\n\nN/A\n\n\n\n\nTicket Status:\n OPEN\n\n\n\n\n\n\nDisplaying your associated emails\u2026\n\n\n\n\nTo:\n \nlanretni.noitadnuof.golc|22koorb.t#lanretni.noitadnuof.golc|22koorb.t\n\n\nFrom:\n \nlanretni.noitadnuof.asiar|ksed.pleh#lanretni.noitadnuof.asiar|ksed.pleh\n\n\nSubject:\n Help Desk Ticket: #5193T3N\n\n\n\n\nMs. Brook,\n\n\nI have been assigned to help resolve your ongoing issue without additional tickets being added to our system. I see that you are having issues accessing the SCP-7684 database entry. Have you confirmed that you are cleared to view it? There are no issues on our end.\n\n\nv/r, Elaine Gerrund\n\n\n\n\n\n\n\n\nTo:\n \nlanretni.noitadnuof.asiar|ksed.pleh#lanretni.noitadnuof.asiar|ksed.pleh\n\n\nFrom:\n \nlanretni.noitadnuof.golc|22koorb.t#lanretni.noitadnuof.golc|22koorb.t\n\n\nSubject:\n Re: Help Desk Ticket: #5193T3N\n\n\n\n\nThank you for finally reaching out. The help system feels like talking to a brick wall (and closing tickets doesn't help either).\n\n\nI \ncannot\n verify access until someone tells me what system to use. It isn't PAGEANT apparently, and it doesn't seem to be the TELTAK either based on shouting from my DSEC's office. Can you just tell me where to check so we can stop bothering you?\n\n\nRespectfully yours,\n\n\nTally F. Brook\n\n\nSupport Analyst, Office of the Regional Director (NA)\n\nDesk: **033-5122-1\n\nMobile: **013-6911-3\n\n\nlanretni.noitadnuof.golc|22koorb.t#lanretni.noitadnuof.golc|22koorb.t\n\n\n\n\n\n\n\n\nTo:\n \nlanretni.noitadnuof.golc|22koorb.t#lanretni.noitadnuof.golc|22koorb.t\n\n\nFrom:\n \nlanretni.noitadnuof.asiar|ksed.pleh#lanretni.noitadnuof.asiar|ksed.pleh\n\n\nSubject:\n Re: Help Desk Ticket: #5193T3N\n\n\n\n\nMs. Brook,\n\n\nUnfortunately, you do not appear to be cleared for any systems that may/may not be capable of validating access to SCP-7684 information, including compartment name and associated personnel. Please have your DSEC contact the RISC office that oversees your portfolio before taking further action.\n\n\nv/r, EG\n\n\n\n\n\n\n\n\nTo:\n \nlanretni.noitadnuof.asiar|ksed.pleh#lanretni.noitadnuof.asiar|ksed.pleh\n\n\nFrom:\n \nlanretni.noitadnuof.golc|22koorb.t#lanretni.noitadnuof.golc|22koorb.t\n\n\nSubject:\n Re: Help Desk Ticket: #5193T3N\n\n\n\n\nWill you please contact the RD/NA RISCO at **808-2221-9 since you seem to understand the problem better than we do?\n\n\n\n\n\n\n\n\nTo:\n \nlanretni.noitadnuof.golc|22koorb.t#lanretni.noitadnuof.golc|22koorb.t\n\n\nFrom:\n \nlanretni.noitadnuof.asiar|ksed.pleh#lanretni.noitadnuof.asiar|ksed.pleh\n\n\nSubject:\n Re: Help Desk Ticket: #5193T3N\n\n\n\n\nMs. Brook,\n\n\nUnfortunately, the RAISA help desk is unable to act as an intermediary in any security matters that do not directly involve our storage systems. This appears to be a transit conflict.\n\n\nv/r, EG\n\n\n\n\n\n\n\n\nTo:\n \nlanretni.noitadnuof.asiar|ksed.pleh#lanretni.noitadnuof.asiar|ksed.pleh\n\n\nFrom:\n \nlanretni.noitadnuof.golc|22koorb.t#lanretni.noitadnuof.golc|22koorb.t\n\n\nSubject:\n Re: Help Desk Ticket: #5193T3N\n\n\n\n\nThis is \nunfortunately\n getting ridiculous considering how many programs our office is read into. What if somebody's life was at risk? The Deputy Assistant Director will be submitting a document request so we can complete these analyses without any extra nonsense. Which subsection of the Foundation Authority Registry is this handled under? And what is the tracking number for the original directive to classify SCP-7684 at this level?\n\n\n\n\n\n\n\n\nTo:\n \nlanretni.noitadnuof.golc|22koorb.t#lanretni.noitadnuof.golc|22koorb.t\n\n\nFrom:\n \nlanretni.noitadnuof.asiar|ksed.pleh#lanretni.noitadnuof.asiar|ksed.pleh\n\n\nSubject:\n Re: Help Desk Ticket: #5193T3N\n\n\n\n\nMs. Brook,\n\n\nRegrettably, information on the original classification determination, subsequent reviews, and related authorities is classified within the same compartment as the SCP-7684 database entry. I do understand this is frustrating. Once you are cleared for access, I will be happy to send more detailed instructions on submitting access requests.\n\n\nv/r, EG\n\n\n\n\n\n\n\n\nOpening latest ticket\u2026\n\n\n\n\nTicket:\n #5AK5TO9\n\n\nDate Filed:\n 06 JUN 2059\n\n\nImportance:\n High\n\n\nSubject:\n SCP-7684 Page Not Pulling from PAGEANT - V4\n\n\nContent:\n\n\n\n\nEscalate ticket #5193T3N to a higher tier of support.\n\n\n\n\nResponse:\n\n\n\n\nUsers cannot open multiple tickets on the same subject unless approved in advance. Please work with your outreach representative to resolve prior tickets.\n\n\n\n\nTicket Status:\n CLOSED\n\n\n\n\n \n\n\n \n\n\n\n\n\n\n\u2021\u00a0Licensing\u00a0/\u00a0Citation\n\n\n\n\n\u2021\u00a0Hide\u00a0Licensing\u00a0/\u00a0Citation\n\n\n\n\nCite this page as:\n\n\n \n\n\n\n\n\"\nSCP-7684\n\" by Pedantique, from the \nSCP Wiki\n. Source: \nhttps://scpwiki.com/scp-7684\n. Licensed under \nCC-BY-SA\n.\n\n\n\n\n\n\n\n\nFor information on how to use this component, see the \nLicense Box component\n. To read about licensing policy, see the \nLicensing Guide\n.",
    "addendums": [],
    "documents": [],
    "notes": [
        "Ticket: #58KG4VO Date Filed: 10 NOV 2058 Importance: Low Subject: SCP-7684 Display Error Content: While reviewing AIC-generated analyses, a redirect to the main SCP-7684 file threw up some errors (not redactions). Can somebody clear this up? Not urgent from my perspective, but it might be for people on the containment team. I'd appreciate a heads up when resolved so I can finish my review. Response: The SCP-7684 page is functioning as intended, but your operational requirement is insufficient to view it. Please consult your security representative. Ticket Status: CLOSED",
        "While reviewing AIC-generated analyses, a redirect to the main SCP-7684 file threw up some errors (not redactions). Can somebody clear this up? Not urgent from my perspective, but it might be for people on the containment team. I'd appreciate a heads up when resolved so I can finish my review.",
        "The SCP-7684 page is functioning as intended, but your operational requirement is insufficient to view it. Please consult your security representative.",
        "Ticket: #O5981A2 Date Filed: 15 NOV 2058 Importance: Medium Subject: SCP-7684 Page Not Pulling from PAGEANT Content: The main SCP-7684 file continues displaying 'OP-REQ INSUFFICIENT' when viewed from any terminal. I consulted my DSEC, and she claims I am good to see scrubbed summaries of everything mainline. Can you confirm that accesses are being validated in PAGEANT? Others on my team had the same issue when double checking. Response: PAGEANT is not certified for processing SCP-7684 accesses. Please consult your security representative to identify proper channels. Ticket Status: CLOSED",
        "The main SCP-7684 file continues displaying 'OP-REQ INSUFFICIENT' when viewed from any terminal. I consulted my DSEC, and she claims I am good to see scrubbed summaries of everything mainline. Can you confirm that accesses are being validated in PAGEANT? Others on my team had the same issue when double checking.",
        "PAGEANT is not certified for processing SCP-7684 accesses. Please consult your security representative to identify proper channels.",
        "Ticket: #9UU351K Date Filed: 03 DEC 2058 Importance: Medium Subject: SCP-7684 Page Not Pulling from PAGEANT - V2 Content: Refer to ticket #O5981A2 for context. My security representative cannot identify the correct system for validating SCP-7684 access. Can you direct me to the proper system/point of contact/etc.? This is getting a little silly even for this place. Response: This tool is not certified to handle that information. Please consult your security representative. Ticket Status: CLOSED",
        "Refer to ticket #O5981A2 for context. My security representative cannot identify the correct system for validating SCP-7684 access. Can you direct me to the proper system/point of contact/etc.? This is getting a little silly even for this place.",
        "This tool is not certified to handle that information. Please consult your security representative.",
        "Ticket: #5193T3N Date Filed: 04 DEC 2058 Importance: High Subject: SCP-7684 Page Not Pulling from PAGEANT - V3! Content: Re: #9UU351K. Not to start a pissing contest, but this is pursuant to a direct tasking from the Deputy Assistant Director for Research and Development (NA). If assistance has to happen at a higher level, someone in your office needs to contact me at lanretni.noitadnuof.golc|22koorb.t#lanretni.noitadnuof.golc|22koorb.t . Response: N/A Ticket Status: OPEN",
        "Re: #9UU351K. Not to start a pissing contest, but this is pursuant to a direct tasking from the Deputy Assistant Director for Research and Development (NA). If assistance has to happen at a higher level, someone in your office needs to contact me at lanretni.noitadnuof.golc|22koorb.t#lanretni.noitadnuof.golc|22koorb.t .",
        "N/A",
        "To: lanretni.noitadnuof.golc|22koorb.t#lanretni.noitadnuof.golc|22koorb.t From: lanretni.noitadnuof.asiar|ksed.pleh#lanretni.noitadnuof.asiar|ksed.pleh Subject: Help Desk Ticket: #5193T3N Ms. Brook, I have been assigned to help resolve your ongoing issue without additional tickets being added to our system. I see that you are having issues accessing the SCP-7684 database entry. Have you confirmed that you are cleared to view it? There are no issues on our end. v/r, Elaine Gerrund",
        "Ms. Brook, I have been assigned to help resolve your ongoing issue without additional tickets being added to our system. I see that you are having issues accessing the SCP-7684 database entry. Have you confirmed that you are cleared to view it? There are no issues on our end. v/r, Elaine Gerrund",
        "To: lanretni.noitadnuof.asiar|ksed.pleh#lanretni.noitadnuof.asiar|ksed.pleh From: lanretni.noitadnuof.golc|22koorb.t#lanretni.noitadnuof.golc|22koorb.t Subject: Re: Help Desk Ticket: #5193T3N Thank you for finally reaching out. The help system feels like talking to a brick wall (and closing tickets doesn't help either). I cannot verify access until someone tells me what system to use. It isn't PAGEANT apparently, and it doesn't seem to be the TELTAK either based on shouting from my DSEC's office. Can you just tell me where to check so we can stop bothering you? Respectfully yours, Tally F. Brook Support Analyst, Office of the Regional Director (NA) Desk: **033-5122-1 Mobile: **013-6911-3 lanretni.noitadnuof.golc|22koorb.t#lanretni.noitadnuof.golc|22koorb.t",
        "Thank you for finally reaching out. The help system feels like talking to a brick wall (and closing tickets doesn't help either). I cannot verify access until someone tells me what system to use. It isn't PAGEANT apparently, and it doesn't seem to be the TELTAK either based on shouting from my DSEC's office. Can you just tell me where to check so we can stop bothering you? Respectfully yours, Tally F. Brook Support Analyst, Office of the Regional Director (NA) Desk: **033-5122-1 Mobile: **013-6911-3 lanretni.noitadnuof.golc|22koorb.t#lanretni.noitadnuof.golc|22koorb.t",
        "To: lanretni.noitadnuof.golc|22koorb.t#lanretni.noitadnuof.golc|22koorb.t From: lanretni.noitadnuof.asiar|ksed.pleh#lanretni.noitadnuof.asiar|ksed.pleh Subject: Re: Help Desk Ticket: #5193T3N Ms. Brook, Unfortunately, you do not appear to be cleared for any systems that may/may not be capable of validating access to SCP-7684 information, including compartment name and associated personnel. Please have your DSEC contact the RISC office that oversees your portfolio before taking further action. v/r, EG",
        "Ms. Brook, Unfortunately, you do not appear to be cleared for any systems that may/may not be capable of validating access to SCP-7684 information, including compartment name and associated personnel. Please have your DSEC contact the RISC office that oversees your portfolio before taking further action. v/r, EG",
        "To: lanretni.noitadnuof.asiar|ksed.pleh#lanretni.noitadnuof.asiar|ksed.pleh From: lanretni.noitadnuof.golc|22koorb.t#lanretni.noitadnuof.golc|22koorb.t Subject: Re: Help Desk Ticket: #5193T3N Will you please contact the RD/NA RISCO at **808-2221-9 since you seem to understand the problem better than we do?",
        "Will you please contact the RD/NA RISCO at **808-2221-9 since you seem to understand the problem better than we do?",
        "To: lanretni.noitadnuof.golc|22koorb.t#lanretni.noitadnuof.golc|22koorb.t From: lanretni.noitadnuof.asiar|ksed.pleh#lanretni.noitadnuof.asiar|ksed.pleh Subject: Re: Help Desk Ticket: #5193T3N Ms. Brook, Unfortunately, the RAISA help desk is unable to act as an intermediary in any security matters that do not directly involve our storage systems. This appears to be a transit conflict. v/r, EG",
        "Ms. Brook, Unfortunately, the RAISA help desk is unable to act as an intermediary in any security matters that do not directly involve our storage systems. This appears to be a transit conflict. v/r, EG",
        "To: lanretni.noitadnuof.asiar|ksed.pleh#lanretni.noitadnuof.asiar|ksed.pleh From: lanretni.noitadnuof.golc|22koorb.t#lanretni.noitadnuof.golc|22koorb.t Subject: Re: Help Desk Ticket: #5193T3N This is unfortunately getting ridiculous considering how many programs our office is read into. What if somebody's life was at risk? The Deputy Assistant Director will be submitting a document request so we can complete these analyses without any extra nonsense. Which subsection of the Foundation Authority Registry is this handled under? And what is the tracking number for the original directive to classify SCP-7684 at this level?",
        "This is unfortunately getting ridiculous considering how many programs our office is read into. What if somebody's life was at risk? The Deputy Assistant Director will be submitting a document request so we can complete these analyses without any extra nonsense. Which subsection of the Foundation Authority Registry is this handled under? And what is the tracking number for the original directive to classify SCP-7684 at this level?",
        "To: lanretni.noitadnuof.golc|22koorb.t#lanretni.noitadnuof.golc|22koorb.t From: lanretni.noitadnuof.asiar|ksed.pleh#lanretni.noitadnuof.asiar|ksed.pleh Subject: Re: Help Desk Ticket: #5193T3N Ms. Brook, Regrettably, information on the original classification determination, subsequent reviews, and related authorities is classified within the same compartment as the SCP-7684 database entry. I do understand this is frustrating. Once you are cleared for access, I will be happy to send more detailed instructions on submitting access requests. v/r, EG",
        "Ms. Brook, Regrettably, information on the original classification determination, subsequent reviews, and related authorities is classified within the same compartment as the SCP-7684 database entry. I do understand this is frustrating. Once you are cleared for access, I will be happy to send more detailed instructions on submitting access requests. v/r, EG",
        "Ticket: #5AK5TO9 Date Filed: 06 JUN 2059 Importance: High Subject: SCP-7684 Page Not Pulling from PAGEANT - V4 Content: Escalate ticket #5193T3N to a higher tier of support. Response: Users cannot open multiple tickets on the same subject unless approved in advance. Please work with your outreach representative to resolve prior tickets. Ticket Status: CLOSED",
        "Escalate ticket #5193T3N to a higher tier of support.",
        "Users cannot open multiple tickets on the same subject unless approved in advance. Please work with your outreach representative to resolve prior tickets.",
        "\" SCP-7684 \" by Pedantique, from the SCP Wiki . Source: https://scpwiki.com/scp-7684 . Licensed under CC-BY-SA ."
    ],
    "item": "SCP-7684",
    "object_class": "[OP-REQ INSUFFICIENT]",
    "containment_procedures": "[OP-REQ INSUFFICIENT]",
    "description": "[OP-REQ INSUFFICIENT]",
    "title": "SCP-7684"
}