{
    "url": "https://scp-wiki.wikidot.com/scp-8145",
    "all_text": "rating:\u00a0\n+90\n+\n\u2013\nx\n\n\nItem #:\n SCP-8145\n\n\nObject Class:\n Keter\n\n\nSpecial Containment Procedures:\n SCP-8145 is contained within its own description.\n\n\nDo not alter, expand or clarify any content of this entry.\n\n\nExercise caution when opening or closing the entry.\n\n\nDescription:\n\n\n\n\n\n\n\n\n\n\n\n\n\n\n\n\n\n\n\n\n\n\n \n\n\n\n\n\n\n\n\n\n\n\n\n\n\n\n\n\n\n\n\n\n\n\n\n\n\n\n\n\n\n\n\n\u00ab \nSCP-8144\n | SCP-8145 | \nSCP-8146\n \u00bb\n\n\n\n\n\n\n\n\n\n\n\u2021\u00a0Licensing\u00a0/\u00a0Citation\n\n\n\n\n\u2021\u00a0Hide\u00a0Licensing\u00a0/\u00a0Citation\n\n\n\n\nCite this page as:\n\n\n \n\n\n\n\n\"\nSCP-8145\n\" by Monkeysky, from the \nSCP Wiki\n. Source: \nhttps://scpwiki.com/scp-8145\n. Licensed under \nCC-BY-SA\n.\n\n\n\n\n\n\n\n\nFor information on how to use this component, see the \nLicense Box component\n. To read about licensing policy, see the \nLicensing Guide\n.\n\n\n\n\nFilename:\n fistula1.svg\n\n\nAuthor:\n \nMonkeysky\n\n\nLicense:\n CC BY-SA 3.0\n\n\nSource Link:\n \nSCP Foundation Wiki\n\n\n\n\n\n\nFilename:\n fistula2.svg\n\n\nAuthor:\n \nMonkeysky\n\n\nLicense:\n CC BY-SA 3.0\n\n\nSource Link:\n \nSCP Foundation Wiki\n\n\n\n\n\n\nFilename:\n fistula3.svg\n\n\nAuthor:\n \nMonkeysky\n\n\nLicense:\n CC BY-SA 3.0\n\n\nSource Link:\n \nSCP Foundation Wiki\n\n\n\n\n\n\nFilename:\n fistula4.svg\n\n\nAuthor:\n \nMonkeysky\n\n\nLicense:\n CC BY-SA 3.0\n\n\nSource Link:\n \nSCP Foundation Wiki\n\n\n\n\n\n\nFilename:\n fistula5.svg\n\n\nAuthor:\n \nMonkeysky\n\n\nLicense:\n CC BY-SA 3.0\n\n\nSource Link:\n \nSCP Foundation Wiki\n\n\n\n\n\n\nFilename:\n fistula6.svg\n\n\nAuthor:\n \nMonkeysky\n\n\nLicense:\n CC BY-SA 3.0\n\n\nSource Link:\n \nSCP Foundation Wiki",
    "addendums": [],
    "documents": [],
    "notes": [
        "\" SCP-8145 \" by Monkeysky, from the SCP Wiki . Source: https://scpwiki.com/scp-8145 . Licensed under CC-BY-SA .",
        "Filename: fistula1.svg Author: Monkeysky License: CC BY-SA 3.0 Source Link: SCP Foundation Wiki",
        "Filename: fistula2.svg Author: Monkeysky License: CC BY-SA 3.0 Source Link: SCP Foundation Wiki",
        "Filename: fistula3.svg Author: Monkeysky License: CC BY-SA 3.0 Source Link: SCP Foundation Wiki",
        "Filename: fistula4.svg Author: Monkeysky License: CC BY-SA 3.0 Source Link: SCP Foundation Wiki",
        "Filename: fistula5.svg Author: Monkeysky License: CC BY-SA 3.0 Source Link: SCP Foundation Wiki",
        "Filename: fistula6.svg Author: Monkeysky License: CC BY-SA 3.0 Source Link: SCP Foundation Wiki"
    ],
    "item": "SCP-8145",
    "object_class": "Keter",
    "containment_procedures": "SCP-8145 is contained within its own description.",
    "description": "",
    "title": "SCP-8145"
}