{
    "url": "https://scp-wiki.wikidot.com/scp-8591",
    "all_text": "PlaguePJP: XLIX\n\n\n\n\n\n\n \n\n\n\n\nrating:\u00a0\n+139\n+\n\u2013\nx\n\n\n\n\n\n\n\u00a0\n\n\n\n\n\u00a0\n\n\n\n\n\n\nSCP-8591\n \u2014 \nAlex Thorley Doesn't Get Away With It\n\n\n\n\n\n\n\n\n\u25b8 More by this Author \u25c2\n\n\n\n\n\n\n\n\n{$comments2}\n\n\n\n\n\n\n \n\n\nF.A.Q.\n\n\n\n\n\n\n{$doesthisfixthebug}\n\n\n\n\n\n\n\n\n\n\n\n\nItem #:\n SCP-8591\n\n\nObject Class:\n Anomalous\n\n\nSpecial Containment Procedures:\n N/A\n\n\n\n\n\n\nSCP-8591.\n\n\n\n\n\n\nDescription:\n SCP-8591 was an adult African Elephant that sporadically appeared and disappeared in Researcher Alex Thorley\u2019s office.\n\n\nAfter the publishing of this documentation, SCP-8591 vanished and has not reappeared in over a year.\n\n\n\n\nTRANSCRIPT\n\n\n\n\nThorley:\n \n(On the phone)\n It\u2019s here again.\n\n\n[\u2026]\n\n\nThorley:\n Maybe it\u2019ll go away.\n\n\n[\u2026]\n\n\nThorley:\n I didn't do \nanything.\n\n\n[\u2026]\n\n\nThorley:\n I didn't do anything wrong.\n\n\n[\u2026]\n\n\nThorley:\n Fine.\n\n\n(Thorley enters their office. There\u2019s an elephant inside.)\n\n\nThorley:\n \u2026I\u2019m addressing you.\n\n\n\n\nRsr. Thorley has been appropriately reprimanded for their undisclosed misconduct prior to this interaction.\n\n\n\n\n\n\n\n\n\u00ab \nSCP-8590\n | SCP-8591 | \nSCP-8592\n \u00bb\n\n\n\n\n\n\n\n\n\n\n\n\nMore\u00a0From\u00a0This\u00a0Author\n\n\n\n\nMore\u00a0From\u00a0This\u00a0Author\n\n\n\n\n\n\n\n\n \n\n\nPlaguePJP's Works\n\n\n\n\n\n\n\n\n\n\nSCPs\n\n\n \n\n\nSCP-8597\n \n(+180)\n \n\u2022\n\n\n\n\n\n\nSCP-618\n \n(+149)\n \n\u2022\n\n\n\n\n\n\nSCP-7001\n \n(+560)\n \n\u2022\n\n\n\n\n\n\nSCP-6595\n \n(+197)\n \n\u2022\n\n\n\n\n\n\nPlauge's Proposal\n \n(+250)\n \n\u2022\n\n\n\n\n\n\nSCP-5595\n \n(+556)\n \n\u2022\n\n\n\n\n\n\nSCP-7591\n \n(+195)\n \n\u2022\n\n\n\n\n\n\nSCP-5592\n \n(+102)\n \n\u2022\n\n\n\n\n\n\nSCP-6592\n \n(+79)\n \n\u2022\n\n\n\n\n\n\nSCP-7592\n \n(+224)\n \n\u2022\n\n\n\n\n\n\nSCP-6597\n \n(+180)\n \n\u2022\n\n\n\n\n\n\nSCP-8594\n \n(+125)\n \n\u2022\n\n\n\n\n\n\nSCP-7599\n \n(+194)\n \n\u2022\n\n\n\n\n\n\nSCP-6598\n \n(+260)\n \n\u2022\n\n\n\n\n\n\nSCP-5594\n \n(+101)\n \n\u2022\n\n\n\n\n\n\n\n\n\n\nTales/GoI Formats\n\n\n \n\n\nHOGSLICE Makes A Friend\n \n(+168)\n \n\u2022\n\n\n\n\n\n\n\n\n\n\nOther\n\n\n \n\n\nPLAGUEPJPAGE\n \n(+204)\n \n\u2022\n\n\n\n\n\n\n\n\n\n\n\n\n\n\n\n\n\n\n\n\n\n\n\u2021\u00a0Licensing\u00a0/\u00a0Citation\n\n\n\n\n\u2021\u00a0Hide\u00a0Licensing\u00a0/\u00a0Citation\n\n\n\n\nCite this page as:\n\n\n \n\n\n\n\n\"\nSCP-8591\n\" by PlaguePJP, from the \nSCP Wiki\n. Source: \nhttps://scpwiki.com/scp-8591\n. Licensed under \nCC-BY-SA\n.\n\n\n\n\n\n\n\n\nFor information on how to use this component, see the \nLicense Box component\n. To read about licensing policy, see the \nLicensing Guide\n.\n\n\n\n\nFilename:\n ellingfant.png\n\n\nLicense:\n CC BY 2.0\n\n\n\n\nThis image is a composite of:\n\n\n\n\nName:\n Elephant\n\n\nAuthor:\n gudi&cris\n\n\nLicense:\n CC BY 2.0\n\n\nSource:\n \nOpenverse",
    "addendums": [],
    "documents": [],
    "notes": [
        "\" SCP-8591 \" by PlaguePJP, from the SCP Wiki . Source: https://scpwiki.com/scp-8591 . Licensed under CC-BY-SA .",
        "Filename: ellingfant.png License: CC BY 2.0",
        "Name: Elephant Author: gudi&cris License: CC BY 2.0 Source: Openverse"
    ],
    "item": "SCP-8591",
    "object_class": "Anomalous",
    "containment_procedures": "N/A",
    "description": "SCP-8591 was an adult African Elephant that sporadically appeared and disappeared in Researcher Alex Thorley\u2019s office.",
    "title": "SCP-8591"
}